Workbook

Sheet Read_Me
A1: INVENTORY STOCK ALERT SYSTEM
A2: Step 1-8 | Complete working model: live status, dashboard, alert report and lookup
A4: Project Objective | B4: Build an inventory monitoring model that identifies products requiring reorder based on current stock and a reorder-level rule.
A5: Step 1 | B5: Created the Excel workbook and structured the inventory data sheet.
A6: Step 2 | B6: Selected and cleaned relevant inventory fields from the uploaded Kaggle dataset.
A7: Step 3 | B7: Prepared a professional inventory master table with 100 latest-snapshot store-product records.
A8: Source | B8: Uploaded Kaggle Retail Store Inventory and Demand Forecasting dataset (retail_store_inventory.csv).
A9: Snapshot Used | B9: Latest available date in the uploaded dataset: 01-Jan-2024.
A10: Reorder Level Rule | B10: The source dataset does not contain a dedicated Reorder Level column. Demand Forecast is therefore used as the derived Reorder Level for this working model.
A11: Step 4 Preview | B11: Stock Status is now calculated live with an Excel formula: REORDER NOW / LOW STOCK / IN STOCK (see Formulas_Used).
A12: Step 4 | B12: Stock Status formula added to Inventory_Data (REORDER NOW / LOW STOCK / IN STOCK) with colour-coded alerts.
A13: Step 5 | B13: Extra data added: Suppliers sheet (lead time, reliability) and Avg Daily Sales per item. Used for days-of-cover, priority and delivery dates.
A14: Step 6 | B14: Calculated columns: Days of Cover, Priority (CRITICAL/HIGH/MEDIUM), Suggested Reorder Qty, Stock Value, Reorder Cost, Expected Delivery, Action.
A15: Step 7 | B15: Dashboard (KPIs, filters, charts, breakdowns, Top 10), Alert_Report (auto-sorted action list) and Stock_Lookup (search any item).
... A19: Sheet guide | B19: Dashboard | Inventory_Data | Alert_Report | Stock_Lookup | Suppliers | Settings | Data_Dictionary | Source_Notes | Formulas_Used

Sheet Dashboard
A1: INVENTORY STOCK ALERT DASHBOARD
A2: ="Report date: "&TEXT(Settings!$B$7,"dd-mmm-yyyy")&" | Filter - Store: "&$B$4&" | Category: "&$E$4 -> Report date: 01-Jan-2024 | Filter - Store: All | Category: All
A4: Store | B4: All | D4: Category | E4: All | H4: <- choose filters from the dropdowns; the KPI cards below update instantly
A6: TOTAL ITEMS | C6: REORDER NOW | E6: LOW STOCK | G6: IN STOCK | I6: STOCK HEALTH % | K6: STOCK VALUE (₹) | M6: EST. REORDER COST (₹)
A7: =COUNTIFS(Inventory_Data!$B$5:$B$104,Settings!$B$10,Inventory_Data!$D$5:$D$104,Settings!$B$11) -> 100 | C7: =COUNTIFS(Inventory_Data!$B$5:$B$104,Settings!$B$10,Inventory_Data!$D$5:$D$104,Settings!$B$11,Inventory_Data!$I$5:$I$104,"REORDER NOW") -> 5 | E7: =COUNTIFS(Inventory_Data!$B$5:$B$104,Settings!$B$10,Inventory_Data!$D$5:$D$104,Settings!$B$11,Inventory_Data!$I$5:$I$104,"LOW STOCK") -> 16 | G7: =COUNTIFS(Inventory_Data!$B$5:$B$104,Settings!$B$10,Inventory_Data!$D$5:$D$104,Settings!$B$11,Inventory_Data!$I$5:$I$104,"IN STOCK") -> 79 | I7: =IFERROR(G7/A7,0) -> 0.79 | K7: =SUMIFS(Inventory_Data!$P$5:$P$104,Inventory_Data!$B$5:$B$104,Settings!$B$10,Inventory_Data!$D$5:$D$104,Settings!$B$11) -> 1410126.9 | M7: =SUMIFS(Inventory_Data!$Q$5:$Q$104,Inventory_Data!$B$5:$B$104,Settings!$B$10,Inventory_Data!$D$5:$D$104,Settings!$B$11) -> 477686.97
A9: ="Rule: REORDER NOW = Stock <= Reorder Level | LOW STOCK = up to "&TEXT(Settings!$B$5,"0%")&" above Reorder Level | IN STOCK = otherwise | CRITICAL = days of cover shorter than supplier lead time" -> Rule: REORDER NOW = Stock <= Reorder Level | LOW STOCK = up to 25% above Reorder Level | IN STOCK = otherwise | CRITICAL = days of cover shorter than supplier lead time
A10: VISUAL OVERVIEW
A28: STOCK STATUS BREAKDOWN (all data)
A29: Store | B29: REORDER NOW | C29: LOW STOCK | D29: IN STOCK | E29: Total | F29: % Needing Alert | H29: Category | I29: REORDER NOW | J29: LOW STOCK | K29: IN STOCK | L29: Total | M29: % Needing Alert
A30: S001 | B30: =COUNTIFS(Inventory_Data!$B$5:$B$104,$A30,Inventory_Data!$I$5:$I$104,B$29) -> 2 | C30: =COUNTIFS(Inventory_Data!$B$5:$B$104,$A30,Inventory_Data!$I$5:$I$104,C$29) -> 0 | D30: =COUNTIFS(Inventory_Data!$B$5:$B$104,$A30,Inventory_Data!$I$5:$I$104,D$29) -> 18 | E30: =SUM(B30:D30) -> 20 | F30: =IFERROR((B30+C30)/E30,0) -> 0.1 | H30: Clothing | I30: =COUNTIFS(Inventory_Data!$D$5:$D$104,$H30,Inventory_Data!$I$5:$I$104,I$29) -> 1 | J30: =COUNTIFS(Inventory_Data!$D$5:$D$104,$H30,Inventory_Data!$I$5:$I$104,J$29) -> 3 | K30: =COUNTIFS(Inventory_Data!$D$5:$D$104,$H30,Inventory_Data!$I$5:$I$104,K$29) -> 10 | L30: =SUM(I30:K30) -> 14 | M30: =IFERROR((I30+J30)/L30,0) -> 0.28571429
A31: S002 | B31: =COUNTIFS(Inventory_Data!$B$5:$B$104,$A31,Inventory_Data!$I$5:$I$104,B$29) -> 0 | C31: =COUNTIFS(Inventory_Data!$B$5:$B$104,$A31,Inventory_Data!$I$5:$I$104,C$29) -> 3 | D31: =COUNTIFS(Inventory_Data!$B$5:$B$104,$A31,Inventory_Data!$I$5:$I$104,D$29) -> 17 | E31: =SUM(B31:D31) -> 20 | F31: =IFERROR((B31+C31)/E31,0) -> 0.15 | H31: Electronics | I31: =COUNTIFS(Inventory_Data!$D$5:$D$104,$H31,Inventory_Data!$I$5:$I$104,I$29) -> 1 | J31: =COUNTIFS(Inventory_Data!$D$5:$D$104,$H31,Inventory_Data!$I$5:$I$104,J$29) -> 2 | K31: =COUNTIFS(Inventory_Data!$D$5:$D$104,$H31,Inventory_Data!$I$5:$I$104,K$29) -> 21 | L31: =SUM(I31:K31) -> 24 | M31: =IFERROR((I31+J31)/L31,0) -> 0.125
A32: S003 | B32: =COUNTIFS(Inventory_Data!$B$5:$B$104,$A32,Inventory_Data!$I$5:$I$104,B$29) -> 1 | C32: =COUNTIFS(Inventory_Data!$B$5:$B$104,$A32,Inventory_Data!$I$5:$I$104,C$29) -> 6 | D32: =COUNTIFS(Inventory_Data!$B$5:$B$104,$A32,Inventory_Data!$I$5:$I$104,D$29) -> 13 | E32: =SUM(B32:D32) -> 20 | F32: =IFERROR((B32+C32)/E32,0) -> 0.35 | H32: Furniture | I32: =COUNTIFS(Inventory_Data!$D$5:$D$104,$H32,Inventory_Data!$I$5:$I$104,I$29) -> 2 | J32: =COUNTIFS(Inventory_Data!$D$5:$D$104,$H32,Inventory_Data!$I$5:$I$104,J$29) -> 6 | K32: =COUNTIFS(Inventory_Data!$D$5:$D$104,$H32,Inventory_Data!$I$5:$I$104,K$29) -> 11 | L32: =SUM(I32:K32) -> 19 | M32: =IFERROR((I32+J32)/L32,0) -> 0.42105263
A33: S004 | B33: =COUNTIFS(Inventory_Data!$B$5:$B$104,$A33,Inventory_Data!$I$5:$I$104,B$29) -> 1 | C33: =COUNTIFS(Inventory_Data!$B$5:$B$104,$A33,Inventory_Data!$I$5:$I$104,C$29) -> 5 | D33: =COUNTIFS(Inventory_Data!$B$5:$B$104,$A33,Inventory_Data!$I$5:$I$104,D$29) -> 14 | E33: =SUM(B33:D33) -> 20 | F33: =IFERROR((B33+C33)/E33,0) -> 0.3 | H33: Groceries | I33: =COUNTIFS(Inventory_Data!$D$5:$D$104,$H33,Inventory_Data!$I$5:$I$104,I$29) -> 0 | J33: =COUNTIFS(Inventory_Data!$D$5:$D$104,$H33,Inventory_Data!$I$5:$I$104,J$29) -> 2 | K33: =COUNTIFS(Inventory_Data!$D$5:$D$104,$H33,Inventory_Data!$I$5:$I$104,K$29) -> 16 | L33: =SUM(I33:K33) -> 18 | M33: =IFERROR((I33+J33)/L33,0) -> 0.11111111
A34: S005 | B34: =COUNTIFS(Inventory_Data!$B$5:$B$104,$A34,Inventory_Data!$I$5:$I$104,B$29) -> 1 | C34: =COUNTIFS(Inventory_Data!$B$5:$B$104,$A34,Inventory_Data!$I$5:$I$104,C$29) -> 2 | D34: =COUNTIFS(Inventory_Data!$B$5:$B$104,$A34,Inventory_Data!$I$5:$I$104,D$29) -> 17 | E34: =SUM(B34:D34) -> 20 | F34: =IFERROR((B34+C34)/E34,0) -> 0.15 | H34: Toys | I34: =COUNTIFS(Inventory_Data!$D$5:$D$104,$H34,Inventory_Data!$I$5:$I$104,I$29) -> 1 | J34: =COUNTIFS(Inventory_Data!$D$5:$D$104,$H34,Inventory_Data!$I$5:$I$104,J$29) -> 3 | K34: =COUNTIFS(Inventory_Data!$D$5:$D$104,$H34,Inventory_Data!$I$5:$I$104,K$29) -> 21 | L34: =SUM(I34:K34) -> 25 | M34: =IFERROR((I34+J34)/L34,0) -> 0.16
A35: TOTAL | B35: =SUM(B30:B34) -> 5 | C35: =SUM(C30:C34) -> 16 | D35: =SUM(D30:D34) -> 79 | E35: =SUM(E30:E34) -> 100 | F35: =IFERROR((B35+C35)/E35,0) -> 0.21 | H35: TOTAL | I35: =SUM(I30:I34) -> 5 | J35: =SUM(J30:J34) -> 16 | K35: =SUM(K30:K34) -> 79 | L35: =SUM(L30:L34) -> 100 | M35: =IFERROR((I35+J35)/L35,0) -> 0.21
A37: Region | B37: REORDER NOW | C37: LOW STOCK | D37: IN STOCK | E37: Total | F37: % Needing Alert | H37: Priority | I37: Items | J37: Units to Order | K37: Order Cost (₹) | L37: Avg Days of Cover | M37: Avg Lead Time (Days)
A38: East | B38: =COUNTIFS(Inventory_Data!$E$5:$E$104,$A38,Inventory_Data!$I$5:$I$104,B$37) -> 1 | C38: =COUNTIFS(Inventory_Data!$E$5:$E$104,$A38,Inventory_Data!$I$5:$I$104,C$37) -> 5 | D38: =COUNTIFS(Inventory_Data!$E$5:$E$104,$A38,Inventory_Data!$I$5:$I$104,D$37) -> 21 | E38: =SUM(B38:D38) -> 27 | F38: =IFERROR((B38+C38)/E38,0) -> 0.22222222 | H38: CRITICAL | I38: =COUNTIFS(Inventory_Data!$N$5:$N$104,$H38) -> 5 | J38: =SUMIFS(Inventory_Data!$O$5:$O$104,Inventory_Data!$N$5:$N$104,$H38) -> 2573 | K38: =SUMIFS(Inventory_Data!$Q$5:$Q$104,Inventory_Data!$N$5:$N$104,$H38) -> 131359.74 | L38: =IFERROR(AVERAGEIFS(Inventory_Data!$M$5:$M$104,Inventory_Data!$N$5:$N$104,$H38),0) -> 7.22 | M38: =IFERROR(AVERAGEIFS(Inventory_Data!$K$5:$K$104,Inventory_Data!$N$5:$N$104,$H38),0) -> 8.6
A39: North | B39: =COUNTIFS(Inventory_Data!$E$5:$E$104,$A39,Inventory_Data!$I$5:$I$104,B$37) -> 1 | C39: =COUNTIFS(Inventory_Data!$E$5:$E$104,$A39,Inventory_Data!$I$5:$I$104,C$37) -> 5 | D39: =COUNTIFS(Inventory_Data!$E$5:$E$104,$A39,Inventory_Data!$I$5:$I$104,D$37) -> 24 | E39: =SUM(B39:D39) -> 30 | F39: =IFERROR((B39+C39)/E39,0) -> 0.2 | H39: HIGH | I39: =COUNTIFS(Inventory_Data!$N$5:$N$104,$H39) -> 2 | J39: =SUMIFS(Inventory_Data!$O$5:$O$104,Inventory_Data!$N$5:$N$104,$H39) -> 381 | K39: =SUMIFS(Inventory_Data!$Q$5:$Q$104,Inventory_Data!$N$5:$N$104,$H39) -> 15570.81 | L39: =IFERROR(AVERAGEIFS(Inventory_Data!$M$5:$M$104,Inventory_Data!$N$5:$N$104,$H39),0) -> 7.2 | M39: =IFERROR(AVERAGEIFS(Inventory_Data!$K$5:$K$104,Inventory_Data!$N$5:$N$104,$H39),0) -> 6
A40: South | B40: =COUNTIFS(Inventory_Data!$E$5:$E$104,$A40,Inventory_Data!$I$5:$I$104,B$37) -> 1 | C40: =COUNTIFS(Inventory_Data!$E$5:$E$104,$A40,Inventory_Data!$I$5:$I$104,C$37) -> 1 | D40: =COUNTIFS(Inventory_Data!$E$5:$E$104,$A40,Inventory_Data!$I$5:$I$104,D$37) -> 12 | E40: =SUM(B40:D40) -> 14 | F40: =IFERROR((B40+C40)/E40,0) -> 0.14285714 | H40: MEDIUM | I40: =COUNTIFS(Inventory_Data!$N$5:$N$104,$H40) -> 14 | J40: =SUMIFS(Inventory_Data!$O$5:$O$104,Inventory_Data!$N$5:$N$104,$H40) -> 5721 | K40: =SUMIFS(Inventory_Data!$Q$5:$Q$104,Inventory_Data!$N$5:$N$104,$H40) -> 330756.42 | L40: =IFERROR(AVERAGEIFS(Inventory_Data!$M$5:$M$104,Inventory_Data!$N$5:$N$104,$H40),0) -> 10.357143 | M40: =IFERROR(AVERAGEIFS(Inventory_Data!$K$5:$K$104,Inventory_Data!$N$5:$N$104,$H40),0) -> 7.8571429
A41: West | B41: =COUNTIFS(Inventory_Data!$E$5:$E$104,$A41,Inventory_Data!$I$5:$I$104,B$37) -> 2 | C41: =COUNTIFS(Inventory_Data!$E$5:$E$104,$A41,Inventory_Data!$I$5:$I$104,C$37) -> 5 | D41: =COUNTIFS(Inventory_Data!$E$5:$E$104,$A41,Inventory_Data!$I$5:$I$104,D$37) -> 22 | E41: =SUM(B41:D41) -> 29 | F41: =IFERROR((B41+C41)/E41,0) -> 0.24137931 | H41: TOTAL | I41: =SUM(I38:I40) -> 21 | J41: =SUM(J38:J40) -> 8675 | K41: =SUM(K38:K40) -> 477686.97 | L41: - | M41: -
A42: TOTAL | B42: =SUM(B38:B41) -> 5 | C42: =SUM(C38:C41) -> 16 | D42: =SUM(D38:D41) -> 79 | E42: =SUM(E38:E41) -> 100 | F42: =IFERROR((B42+C42)/E42,0) -> 0.21
A45: TOP 10 PRIORITY ALERTS (all stores, ranked by urgency)
A46: Rank | B46: Store | C46: Product ID | D46: Category | E46: Current Stock | F46: Reorder Level | G46: Status | H46: Priority | I46: Days of Cover | J46: Lead Time (Days) | K46: Supplier | L46: Qty to Order | M46: Est. Cost (₹) | N46: Recommended Action
A47: 1 | B47: =IFERROR(INDEX(Inventory_Data!$B$5:$B$104,MATCH($A47,Inventory_Data!$U$5:$U$104,0)),"") -> S005 | C47: =IFERROR(INDEX(Inventory_Data!$C$5:$C$104,MATCH($A47,Inventory_Data!$U$5:$U$104,0)),"") -> P0003 | D47: =IFERROR(INDEX(Inventory_Data!$D$5:$D$104,MATCH($A47,Inventory_Data!$U$5:$U$104,0)),"") -> Furniture | E47: =IFERROR(INDEX(Inventory_Data!$F$5:$F$104,MATCH($A47,Inventory_Data!$U$5:$U$104,0)),"") -> 98 | F47: =IFERROR(INDEX(Inventory_Data!$G$5:$G$104,MATCH($A47,Inventory_Data!$U$5:$U$104,0)),"") -> 106 | G47: =IFERROR(INDEX(Inventory_Data!$I$5:$I$104,MATCH($A47,Inventory_Data!$U$5:$U$104,0)),"") -> REORDER NOW | H47: =IFERROR(INDEX(Inventory_Data!$N$5:$N$104,MATCH($A47,Inventory_Data!$U$5:$U$104,0)),"") -> CRITICAL | I47: =IFERROR(INDEX(Inventory_Data!$M$5:$M$104,MATCH($A47,Inventory_Data!$U$5:$U$104,0)),"") -> 10.5 | J47: =IFERROR(INDEX(Inventory_Data!$K$5:$K$104,MATCH($A47,Inventory_Data!$U$5:$U$104,0)),"") -> 12 | K47: =IFERROR(INDEX(Inventory_Data!$J$5:$J$104,MATCH($A47,Inventory_Data!$U$5:$U$104,0)),"") -> HomeCraft Suppliers | L47: =IFERROR(INDEX(Inventory_Data!$O$5:$O$104,MATCH($A47,Inventory_Data!$U$5:$U$104,0)),"") -> 220 | M47: =IFERROR(INDEX(Inventory_Data!$Q$5:$Q$104,MATCH($A47,Inventory_Data!$U$5:$U$104,0)),"") -> 5317.4 | N47: =IFERROR(INDEX(Inventory_Data!$S$5:$S$104,MATCH($A47,Inventory_Data!$U$5:$U$104,0)),"") -> Order immediately - stock-out before delivery
A48: 2 | B48: =IFERROR(INDEX(Inventory_Data!$B$5:$B$104,MATCH($A48,Inventory_Data!$U$5:$U$104,0)),"") -> S004 | C48: =IFERROR(INDEX(Inventory_Data!$C$5:$C$104,MATCH($A48,Inventory_Data!$U$5:$U$104,0)),"") -> P0002 | D48: =IFERROR(INDEX(Inventory_Data!$D$5:$D$104,MATCH($A48,Inventory_Data!$U$5:$U$104,0)),"") -> Furniture | E48: =IFERROR(INDEX(Inventory_Data!$F$5:$F$104,MATCH($A48,Inventory_Data!$U$5:$U$104,0)),"") -> 181 | F48: =IFERROR(INDEX(Inventory_Data!$G$5:$G$104,MATCH($A48,Inventory_Data!$U$5:$U$104,0)),"") -> 193 | G48: =IFERROR(INDEX(Inventory_Data!$I$5:$I$104,MATCH($A48,Inventory_Data!$U$5:$U$104,0)),"") -> REORDER NOW | H48: =IFERROR(INDEX(Inventory_Data!$N$5:$N$104,MATCH($A48,Inventory_Data!$U$5:$U$104,0)),"") -> CRITICAL | I48: =IFERROR(INDEX(Inventory_Data!$M$5:$M$104,MATCH($A48,Inventory_Data!$U$5:$U$104,0)),"") -> 10.4 | J48: =IFERROR(INDEX(Inventory_Data!$K$5:$K$104,MATCH($A48,Inventory_Data!$U$5:$U$104,0)),"") -> 12 | K48: =IFERROR(INDEX(Inventory_Data!$J$5:$J$104,MATCH($A48,Inventory_Data!$U$5:$U$104,0)),"") -> HomeCraft Suppliers | L48: =IFERROR(INDEX(Inventory_Data!$O$5:$O$104,MATCH($A48,Inventory_Data!$U$5:$U$104,0)),"") -> 398 | M48: =IFERROR(INDEX(Inventory_Data!$Q$5:$Q$104,MATCH($A48,Inventory_Data!$U$5:$U$104,0)),"") -> 12198.7 | N48: =IFERROR(INDEX(Inventory_Data!$S$5:$S$104,MATCH($A48,Inventory_Data!$U$5:$U$104,0)),"") -> Order immediately - stock-out before delivery
A49: 3 | B49: =IFERROR(INDEX(Inventory_Data!$B$5:$B$104,MATCH($A49,Inventory_Data!$U$5:$U$104,0)),"") -> S001 | C49: =IFERROR(INDEX(Inventory_Data!$C$5:$C$104,MATCH($A49,Inventory_Data!$U$5:$U$104,0)),"") -> P0019 | D49: =IFERROR(INDEX(Inventory_Data!$D$5:$D$104,MATCH($A49,Inventory_Data!$U$5:$U$104,0)),"") -> Clothing | E49: =IFERROR(INDEX(Inventory_Data!$F$5:$F$104,MATCH($A49,Inventory_Data!$U$5:$U$104,0)),"") -> 149 | F49: =IFERROR(INDEX(Inventory_Data!$G$5:$G$104,MATCH($A49,Inventory_Data!$U$5:$U$104,0)),"") -> 155 | G49: =IFERROR(INDEX(Inventory_Data!$I$5:$I$104,MATCH($A49,Inventory_Data!$U$5:$U$104,0)),"") -> REORDER NOW | H49: =IFERROR(INDEX(Inventory_Data!$N$5:$N$104,MATCH($A49,Inventory_Data!$U$5:$U$104,0)),"") -> CRITICAL | I49: =IFERROR(INDEX(Inventory_Data!$M$5:$M$104,MATCH($A49,Inventory_Data!$U$5:$U$104,0)),"") -> 4.9 | J49: =IFERROR(INDEX(Inventory_Data!$K$5:$K$104,MATCH($A49,Inventory_Data!$U$5:$U$104,0)),"") -> 6 | K49: =IFERROR(INDEX(Inventory_Data!$J$5:$J$104,MATCH($A49,Inventory_Data!$U$5:$U$104,0)),"") -> StyleHub Wholesale | L49: =IFERROR(INDEX(Inventory_Data!$O$5:$O$104,MATCH($A49,Inventory_Data!$U$5:$U$104,0)),"") -> 316 | M49: =IFERROR(INDEX(Inventory_Data!$Q$5:$Q$104,MATCH($A49,Inventory_Data!$U$5:$U$104,0)),"") -> 25820.36 | N49: =IFERROR(INDEX(Inventory_Data!$S$5:$S$104,MATCH($A49,Inventory_Data!$U$5:$U$104,0)),"") -> Order immediately - stock-out before delivery
A50: 4 | B50: =IFERROR(INDEX(Inventory_Data!$B$5:$B$104,MATCH($A50,Inventory_Data!$U$5:$U$104,0)),"") -> S004 | C50: =IFERROR(INDEX(Inventory_Data!$C$5:$C$104,MATCH($A50,Inventory_Data!$U$5:$U$104,0)),"") -> P0001 | D50: =IFERROR(INDEX(Inventory_Data!$D$5:$D$104,MATCH($A50,Inventory_Data!$U$5:$U$104,0)),"") -> Electronics | E50: =IFERROR(INDEX(Inventory_Data!$F$5:$F$104,MATCH($A50,Inventory_Data!$U$5:$U$104,0)),"") -> 497 | F50: =IFERROR(INDEX(Inventory_Data!$G$5:$G$104,MATCH($A50,Inventory_Data!$U$5:$U$104,0)),"") -> 490 | G50: =IFERROR(INDEX(Inventory_Data!$I$5:$I$104,MATCH($A50,Inventory_Data!$U$5:$U$104,0)),"") -> LOW STOCK | H50: =IFERROR(INDEX(Inventory_Data!$N$5:$N$104,MATCH($A50,Inventory_Data!$U$5:$U$104,0)),"") -> CRITICAL | I50: =IFERROR(INDEX(Inventory_Data!$M$5:$M$104,MATCH($A50,Inventory_Data!$U$5:$U$104,0)),"") -> 5.5 | J50: =IFERROR(INDEX(Inventory_Data!$K$5:$K$104,MATCH($A50,Inventory_Data!$U$5:$U$104,0)),"") -> 7 | K50: =IFERROR(INDEX(Inventory_Data!$J$5:$J$104,MATCH($A50,Inventory_Data!$U$5:$U$104,0)),"") -> TechSource India | L50: =IFERROR(INDEX(Inventory_Data!$O$5:$O$104,MATCH($A50,Inventory_Data!$U$5:$U$104,0)),"") -> 973 | M50: =IFERROR(INDEX(Inventory_Data!$Q$5:$Q$104,MATCH($A50,Inventory_Data!$U$5:$U$104,0)),"") -> 41196.82 | N50: =IFERROR(INDEX(Inventory_Data!$S$5:$S$104,MATCH($A50,Inventory_Data!$U$5:$U$104,0)),"") -> Order immediately - stock-out before delivery
A51: 5 | B51: =IFERROR(INDEX(Inventory_Data!$B$5:$B$104,MATCH($A51,Inventory_Data!$U$5:$U$104,0)),"") -> S002 | C51: =IFERROR(INDEX(Inventory_Data!$C$5:$C$104,MATCH($A51,Inventory_Data!$U$5:$U$104,0)),"") -> P0014 | D51: =IFERROR(INDEX(Inventory_Data!$D$5:$D$104,MATCH($A51,Inventory_Data!$U$5:$U$104,0)),"") -> Clothing | E51: =IFERROR(INDEX(Inventory_Data!$F$5:$F$104,MATCH($A51,Inventory_Data!$U$5:$U$104,0)),"") -> 342 | F51: =IFERROR(INDEX(Inventory_Data!$G$5:$G$104,MATCH($A51,Inventory_Data!$U$5:$U$104,0)),"") -> 336 | G51: =IFERROR(INDEX(Inventory_Data!$I$5:$I$104,MATCH($A51,Inventory_Data!$U$5:$U$104,0)),"") -> LOW STOCK | H51: =IFERROR(INDEX(Inventory_Data!$N$5:$N$104,MATCH($A51,Inventory_Data!$U$5:$U$104,0)),"") -> CRITICAL | I51: =IFERROR(INDEX(Inventory_Data!$M$5:$M$104,MATCH($A51,Inventory_Data!$U$5:$U$104,0)),"") -> 4.8 | J51: =IFERROR(INDEX(Inventory_Data!$K$5:$K$104,MATCH($A51,Inventory_Data!$U$5:$U$104,0)),"") -> 6 | K51: =IFERROR(INDEX(Inventory_Data!$J$5:$J$104,MATCH($A51,Inventory_Data!$U$5:$U$104,0)),"") -> StyleHub Wholesale | L51: =IFERROR(INDEX(Inventory_Data!$O$5:$O$104,MATCH($A51,Inventory_Data!$U$5:$U$104,0)),"") -> 666 | M51: =IFERROR(INDEX(Inventory_Data!$Q$5:$Q$104,MATCH($A51,Inventory_Data!$U$5:$U$104,0)),"") -> 46826.46 | N51: =IFERROR(INDEX(Inventory_Data!$S$5:$S$104,MATCH($A51,Inventory_Data!$U$5:$U$104,0)),"") -> Order immediately - stock-out before delivery
A52: 6 | B52: =IFERROR(INDEX(Inventory_Data!$B$5:$B$104,MATCH($A52,Inventory_Data!$U$5:$U$104,0)),"") -> S001 | C52: =IFERROR(INDEX(Inventory_Data!$C$5:$C$104,MATCH($A52,Inventory_Data!$U$5:$U$104,0)),"") -> P0003 | D52: =IFERROR(INDEX(Inventory_Data!$D$5:$D$104,MATCH($A52,Inventory_Data!$U$5:$U$104,0)),"") -> Toys | E52: =IFERROR(INDEX(Inventory_Data!$F$5:$F$104,MATCH($A52,Inventory_Data!$U$5:$U$104,0)),"") -> 69 | F52: =IFERROR(INDEX(Inventory_Data!$G$5:$G$104,MATCH($A52,Inventory_Data!$U$5:$U$104,0)),"") -> 77 | G52: =IFERROR(INDEX(Inventory_Data!$I$5:$I$104,MATCH($A52,Inventory_Data!$U$5:$U$104,0)),"") -> REORDER NOW | H52: =IFERROR(INDEX(Inventory_Data!$N$5:$N$104,MATCH($A52,Inventory_Data!$U$5:$U$104,0)),"") -> HIGH | I52: =IFERROR(INDEX(Inventory_Data!$M$5:$M$104,MATCH($A52,Inventory_Data!$U$5:$U$104,0)),"") -> 5.2 | J52: =IFERROR(INDEX(Inventory_Data!$K$5:$K$104,MATCH($A52,Inventory_Data!$U$5:$U$104,0)),"") -> 5 | K52: =IFERROR(INDEX(Inventory_Data!$J$5:$J$104,MATCH($A52,Inventory_Data!$U$5:$U$104,0)),"") -> PlayWorld Distributors | L52: =IFERROR(INDEX(Inventory_Data!$O$5:$O$104,MATCH($A52,Inventory_Data!$U$5:$U$104,0)),"") -> 162 | M52: =IFERROR(INDEX(Inventory_Data!$Q$5:$Q$104,MATCH($A52,Inventory_Data!$U$5:$U$104,0)),"") -> 3554.28 | N52: =IFERROR(INDEX(Inventory_Data!$S$5:$S$104,MATCH($A52,Inventory_Data!$U$5:$U$104,0)),"") -> Raise purchase order today
A53: 7 | B53: =IFERROR(INDEX(Inventory_Data!$B$5:$B$104,MATCH($A53,Inventory_Data!$U$5:$U$104,0)),"") -> S003 | C53: =IFERROR(INDEX(Inventory_Data!$C$5:$C$104,MATCH($A53,Inventory_Data!$U$5:$U$104,0)),"") -> P0007 | D53: =IFERROR(INDEX(Inventory_Data!$D$5:$D$104,MATCH($A53,Inventory_Data!$U$5:$U$104,0)),"") -> Electronics | E53: =IFERROR(INDEX(Inventory_Data!$F$5:$F$104,MATCH($A53,Inventory_Data!$U$5:$U$104,0)),"") -> 108 | F53: =IFERROR(INDEX(Inventory_Data!$G$5:$G$104,MATCH($A53,Inventory_Data!$U$5:$U$104,0)),"") -> 109 | G53: =IFERROR(INDEX(Inventory_Data!$I$5:$I$104,MATCH($A53,Inventory_Data!$U$5:$U$104,0)),"") -> REORDER NOW | H53: =IFERROR(INDEX(Inventory_Data!$N$5:$N$104,MATCH($A53,Inventory_Data!$U$5:$U$104,0)),"") -> HIGH | I53: =IFERROR(INDEX(Inventory_Data!$M$5:$M$104,MATCH($A53,Inventory_Data!$U$5:$U$104,0)),"") -> 9.2 | J53: =IFERROR(INDEX(Inventory_Data!$K$5:$K$104,MATCH($A53,Inventory_Data!$U$5:$U$104,0)),"") -> 7 | K53: =IFERROR(INDEX(Inventory_Data!$J$5:$J$104,MATCH($A53,Inventory_Data!$U$5:$U$104,0)),"") -> TechSource India | L53: =IFERROR(INDEX(Inventory_Data!$O$5:$O$104,MATCH($A53,Inventory_Data!$U$5:$U$104,0)),"") -> 219 | M53: =IFERROR(INDEX(Inventory_Data!$Q$5:$Q$104,MATCH($A53,Inventory_Data!$U$5:$U$104,0)),"") -> 12016.53 | N53: =IFERROR(INDEX(Inventory_Data!$S$5:$S$104,MATCH($A53,Inventory_Data!$U$5:$U$104,0)),"") -> Raise purchase order today
A54: 8 | B54: =IFERROR(INDEX(Inventory_Data!$B$5:$B$104,MATCH($A54,Inventory_Data!$U$5:$U$104,0)),"") -> S004 | C54: =IFERROR(INDEX(Inventory_Data!$C$5:$C$104,MATCH($A54,Inventory_Data!$U$5:$U$104,0)),"") -> P0020 | D54: =IFERROR(INDEX(Inventory_Data!$D$5:$D$104,MATCH($A54,Inventory_Data!$U$5:$U$104,0)),"") -> Toys | E54: =IFERROR(INDEX(Inventory_Data!$F$5:$F$104,MATCH($A54,Inventory_Data!$U$5:$U$104,0)),"") -> 249 | F54: =IFERROR(INDEX(Inventory_Data!$G$5:$G$104,MATCH($A54,Inventory_Data!$U$5:$U$104,0)),"") -> 248 | G54: =IFERROR(INDEX(Inventory_Data!$I$5:$I$104,MATCH($A54,Inventory_Data!$U$5:$U$104,0)),"") -> LOW STOCK | H54: =IFERROR(INDEX(Inventory_Data!$N$5:$N$104,MATCH($A54,Inventory_Data!$U$5:$U$104,0)),"") -> MEDIUM | I54: =IFERROR(INDEX(Inventory_Data!$M$5:$M$104,MATCH($A54,Inventory_Data!$U$5:$U$104,0)),"") -> 5.9 | J54: =IFERROR(INDEX(Inventory_Data!$K$5:$K$104,MATCH($A54,Inventory_Data!$U$5:$U$104,0)),"") -> 5 | K54: =IFERROR(INDEX(Inventory_Data!$J$5:$J$104,MATCH($A54,Inventory_Data!$U$5:$U$104,0)),"") -> PlayWorld Distributors | L54: =IFERROR(INDEX(Inventory_Data!$O$5:$O$104,MATCH($A54,Inventory_Data!$U$5:$U$104,0)),"") -> 495 | M54: =IFERROR(INDEX(Inventory_Data!$Q$5:$Q$104,MATCH($A54,Inventory_Data!$U$5:$U$104,0)),"") -> 16270.65 | N54: =IFERROR(INDEX(Inventory_Data!$S$5:$S$104,MATCH($A54,Inventory_Data!$U$5:$U$104,0)),"") -> Plan reorder this week
A55: 9 | B55: =IFERROR(INDEX(Inventory_Data!$B$5:$B$104,MATCH($A55,Inventory_Data!$U$5:$U$104,0)),"") -> S003 | C55: =IFERROR(INDEX(Inventory_Data!$C$5:$C$104,MATCH($A55,Inventory_Data!$U$5:$U$104,0)),"") -> P0010 | D55: =IFERROR(INDEX(Inventory_Data!$D$5:$D$104,MATCH($A55,Inventory_Data!$U$5:$U$104,0)),"") -> Furniture | E55: =IFERROR(INDEX(Inventory_Data!$F$5:$F$104,MATCH($A55,Inventory_Data!$U$5:$U$104,0)),"") -> 413 | F55: =IFERROR(INDEX(Inventory_Data!$G$5:$G$104,MATCH($A55,Inventory_Data!$U$5:$U$104,0)),"") -> 409 | G55: =IFERROR(INDEX(Inventory_Data!$I$5:$I$104,MATCH($A55,Inventory_Data!$U$5:$U$104,0)),"") -> LOW STOCK | H55: =IFERROR(INDEX(Inventory_Data!$N$5:$N$104,MATCH($A55,Inventory_Data!$U$5:$U$104,0)),"") -> MEDIUM | I55: =IFERROR(INDEX(Inventory_Data!$M$5:$M$104,MATCH($A55,Inventory_Data!$U$5:$U$104,0)),"") -> 13.2 | J55: =IFERROR(INDEX(Inventory_Data!$K$5:$K$104,MATCH($A55,Inventory_Data!$U$5:$U$104,0)),"") -> 12 | K55: =IFERROR(INDEX(Inventory_Data!$J$5:$J$104,MATCH($A55,Inventory_Data!$U$5:$U$104,0)),"") -> HomeCraft Suppliers | L55: =IFERROR(INDEX(Inventory_Data!$O$5:$O$104,MATCH($A55,Inventory_Data!$U$5:$U$104,0)),"") -> 814 | M55: =IFERROR(INDEX(Inventory_Data!$Q$5:$Q$104,MATCH($A55,Inventory_Data!$U$5:$U$104,0)),"") -> 65828.18 | N55: =IFERROR(INDEX(Inventory_Data!$S$5:$S$104,MATCH($A55,Inventory_Data!$U$5:$U$104,0)),"") -> Plan reorder this week
A56: 10 | B56: =IFERROR(INDEX(Inventory_Data!$B$5:$B$104,MATCH($A56,Inventory_Data!$U$5:$U$104,0)),"") -> S004 | C56: =IFERROR(INDEX(Inventory_Data!$C$5:$C$104,MATCH($A56,Inventory_Data!$U$5:$U$104,0)),"") -> P0008 | D56: =IFERROR(INDEX(Inventory_Data!$D$5:$D$104,MATCH($A56,Inventory_Data!$U$5:$U$104,0)),"") -> Furniture | E56: =IFERROR(INDEX(Inventory_Data!$F$5:$F$104,MATCH($A56,Inventory_Data!$U$5:$U$104,0)),"") -> 390 | F56: =IFERROR(INDEX(Inventory_Data!$G$5:$G$104,MATCH($A56,Inventory_Data!$U$5:$U$104,0)),"") -> 369 | G56: =IFERROR(INDEX(Inventory_Data!$I$5:$I$104,MATCH($A56,Inventory_Data!$U$5:$U$104,0)),"") -> LOW STOCK | H56: =IFERROR(INDEX(Inventory_Data!$N$5:$N$104,MATCH($A56,Inventory_Data!$U$5:$U$104,0)),"") -> MEDIUM | I56: =IFERROR(INDEX(Inventory_Data!$M$5:$M$104,MATCH($A56,Inventory_Data!$U$5:$U$104,0)),"") -> 17.6 | J56: =IFERROR(INDEX(Inventory_Data!$K$5:$K$104,MATCH($A56,Inventory_Data!$U$5:$U$104,0)),"") -> 12 | K56: =IFERROR(INDEX(Inventory_Data!$J$5:$J$104,MATCH($A56,Inventory_Data!$U$5:$U$104,0)),"") -> HomeCraft Suppliers | L56: =IFERROR(INDEX(Inventory_Data!$O$5:$O$104,MATCH($A56,Inventory_Data!$U$5:$U$104,0)),"") -> 717 | M56: =IFERROR(INDEX(Inventory_Data!$Q$5:$Q$104,MATCH($A56,Inventory_Data!$U$5:$U$104,0)),"") -> 57833.22 | N56: =IFERROR(INDEX(Inventory_Data!$S$5:$S$104,MATCH($A56,Inventory_Data!$U$5:$U$104,0)),"") -> Plan reorder this week

Sheet Inventory_Data
A1: INVENTORY STOCK ALERT SYSTEM
A2: Latest inventory snapshot | Stock Status & alert columns are live formulas | Blue = assumed input, Black = formula, Grey header = helper columns
A4: Date | B4: Store ID | C4: Product ID | D4: Category | E4: Region | F4: Current Stock | G4: Reorder Level | H4: Unit Price (₹) | I4: Stock Status | J4: Supplier | K4: Lead Time (Days) | L4: Avg Daily Sales (Units) | M4: Days of Cover | N4: Priority | O4: Suggested Reorder Qty | P4: Stock Value (₹) | Q4: Reorder Cost (₹) | R4: Expected Delivery | S4: Recommended Action | T4: Priority Score (helper) | U4: Alert Rank (helper)
A5: 45292 | B5: S001 | C5: P0001 | D5: Toys | E5: East | F5: 223 | G5: 54 | H5: 55.26 | I5: =IF(F5<=G5,"REORDER NOW",IF(F5<=G5*(1+Settings!$B$5),"LOW STOCK","IN STOCK")) -> IN STOCK | J5: =IFERROR(INDEX(Suppliers!$B$5:$B$9,MATCH(D5,Suppliers!$C$5:$C$9,0)),"Unassigned") -> PlayWorld Distributors | K5: =IFERROR(INDEX(Suppliers!$D$5:$D$9,MATCH(D5,Suppliers!$C$5:$C$9,0)),0) -> 5 | L5: 11.7 | M5: =IF(L5>0,ROUND(F5/L5,1),"") -> 19.1 | N5: =IF(I5="IN STOCK","-",IF(AND(M5<>"",M5<K5),"CRITICAL",IF(I5="REORDER NOW","HIGH","MEDIUM"))) -> - | O5: =IF(I5="IN STOCK",0,MAX(0,ROUNDUP(G5*Settings!$B$6,0)-F5)) -> 0 | P5: =F5*H5 -> 12322.98 | Q5: =O5*H5 -> 0 | R5: =IF(I5="IN STOCK","",Settings!$B$7+K5) | S5: =IF(N5="CRITICAL","Order immediately - stock-out before delivery",IF(N5="HIGH","Raise purchase order today",IF(N5="MEDIUM","Plan reorder this week","No action required"))) -> No action required | T5: =IF(I5="IN STOCK",0,IF(N5="CRITICAL",30,IF(N5="HIGH",20,10))+IF(G5>0,(G5-F5)/G5,0)+ROW()/10000000) -> 0 | U5: =IF(T5>0,SUMPRODUCT(--($T$5:$T$104>T5))+1,"")
A6: 45292 | B6: S001 | C6: P0002 | D6: Furniture | E6: West | F6: 217 | G6: 101 | H6: 44.84 | I6: =IF(F6<=G6,"REORDER NOW",IF(F6<=G6*(1+Settings!$B$5),"LOW STOCK","IN STOCK")) -> IN STOCK | J6: =IFERROR(INDEX(Suppliers!$B$5:$B$9,MATCH(D6,Suppliers!$C$5:$C$9,0)),"Unassigned") -> HomeCraft Suppliers | K6: =IFERROR(INDEX(Suppliers!$D$5:$D$9,MATCH(D6,Suppliers!$C$5:$C$9,0)),0) -> 12 | L6: 6 | M6: =IF(L6>0,ROUND(F6/L6,1),"") -> 36.2 | N6: =IF(I6="IN STOCK","-",IF(AND(M6<>"",M6<K6),"CRITICAL",IF(I6="REORDER NOW","HIGH","MEDIUM"))) -> - | O6: =IF(I6="IN STOCK",0,MAX(0,ROUNDUP(G6*Settings!$B$6,0)-F6)) -> 0 | P6: =F6*H6 -> 9730.28 | Q6: =O6*H6 -> 0 | R6: =IF(I6="IN STOCK","",Settings!$B$7+K6) | S6: =IF(N6="CRITICAL","Order immediately - stock-out before delivery",IF(N6="HIGH","Raise purchase order today",IF(N6="MEDIUM","Plan reorder this week","No action required"))) -> No action required | T6: =IF(I6="IN STOCK",0,IF(N6="CRITICAL",30,IF(N6="HIGH",20,10))+IF(G6>0,(G6-F6)/G6,0)+ROW()/10000000) -> 0 | U6: =IF(T6>0,SUMPRODUCT(--($T$5:$T$104>T6))+1,"")
A7: 45292 | B7: S001 | C7: P0003 | D7: Toys | E7: East | F7: 69 | G7: 77 | H7: 21.94 | I7: =IF(F7<=G7,"REORDER NOW",IF(F7<=G7*(1+Settings!$B$5),"LOW STOCK","IN STOCK")) -> REORDER NOW | J7: =IFERROR(INDEX(Suppliers!$B$5:$B$9,MATCH(D7,Suppliers!$C$5:$C$9,0)),"Unassigned") -> PlayWorld Distributors | K7: =IFERROR(INDEX(Suppliers!$D$5:$D$9,MATCH(D7,Suppliers!$C$5:$C$9,0)),0) -> 5 | L7: 13.3 | M7: =IF(L7>0,ROUND(F7/L7,1),"") -> 5.2 | N7: =IF(I7="IN STOCK","-",IF(AND(M7<>"",M7<K7),"CRITICAL",IF(I7="REORDER NOW","HIGH","MEDIUM"))) -> HIGH | O7: =IF(I7="IN STOCK",0,MAX(0,ROUNDUP(G7*Settings!$B$6,0)-F7)) -> 162 | P7: =F7*H7 -> 1513.86 | Q7: =O7*H7 -> 3554.28 | R7: =IF(I7="IN STOCK","",Settings!$B$7+K7) -> 45297 | S7: =IF(N7="CRITICAL","Order immediately - stock-out before delivery",IF(N7="HIGH","Raise purchase order today",IF(N7="MEDIUM","Plan reorder this week","No action required"))) -> Raise purchase order today | T7: =IF(I7="IN STOCK",0,IF(N7="CRITICAL",30,IF(N7="HIGH",20,10))+IF(G7>0,(G7-F7)/G7,0)+ROW()/10000000) -> 20.103897 | U7: =IF(T7>0,SUMPRODUCT(--($T$5:$T$104>T7))+1,"") -> 6
A8: 45292 | B8: S001 | C8: P0004 | D8: Groceries | E8: West | F8: 338 | G8: 192 | H8: 86.37 | I8: =IF(F8<=G8,"REORDER NOW",IF(F8<=G8*(1+Settings!$B$5),"LOW STOCK","IN STOCK")) -> IN STOCK | J8: =IFERROR(INDEX(Suppliers!$B$5:$B$9,MATCH(D8,Suppliers!$C$5:$C$9,0)),"Unassigned") -> FreshLink Traders | K8: =IFERROR(INDEX(Suppliers!$D$5:$D$9,MATCH(D8,Suppliers!$C$5:$C$9,0)),0) -> 2 | L8: 80.1 | M8: =IF(L8>0,ROUND(F8/L8,1),"") -> 4.2 | N8: =IF(I8="IN STOCK","-",IF(AND(M8<>"",M8<K8),"CRITICAL",IF(I8="REORDER NOW","HIGH","MEDIUM"))) -> - | O8: =IF(I8="IN STOCK",0,MAX(0,ROUNDUP(G8*Settings!$B$6,0)-F8)) -> 0 | P8: =F8*H8 -> 29193.06 | Q8: =O8*H8 -> 0 | R8: =IF(I8="IN STOCK","",Settings!$B$7+K8) | S8: =IF(N8="CRITICAL","Order immediately - stock-out before delivery",IF(N8="HIGH","Raise purchase order today",IF(N8="MEDIUM","Plan reorder this week","No action required"))) -> No action required | T8: =IF(I8="IN STOCK",0,IF(N8="CRITICAL",30,IF(N8="HIGH",20,10))+IF(G8>0,(G8-F8)/G8,0)+ROW()/10000000) -> 0 | U8: =IF(T8>0,SUMPRODUCT(--($T$5:$T$104>T8))+1,"")
A9: 45292 | B9: S001 | C9: P0005 | D9: Groceries | E9: North | F9: 471 | G9: 267 | H9: 15.58 | I9: =IF(F9<=G9,"REORDER NOW",IF(F9<=G9*(1+Settings!$B$5),"LOW STOCK","IN STOCK")) -> IN STOCK | J9: =IFERROR(INDEX(Suppliers!$B$5:$B$9,MATCH(D9,Suppliers!$C$5:$C$9,0)),"Unassigned") -> FreshLink Traders | K9: =IFERROR(INDEX(Suppliers!$D$5:$D$9,MATCH(D9,Suppliers!$C$5:$C$9,0)),0) -> 2 | L9: 152.4 | M9: =IF(L9>0,ROUND(F9/L9,1),"") -> 3.1 | N9: =IF(I9="IN STOCK","-",IF(AND(M9<>"",M9<K9),"CRITICAL",IF(I9="REORDER NOW","HIGH","MEDIUM"))) -> - | O9: =IF(I9="IN STOCK",0,MAX(0,ROUNDUP(G9*Settings!$B$6,0)-F9)) -> 0 | P9: =F9*H9 -> 7338.18 | Q9: =O9*H9 -> 0 | R9: =IF(I9="IN STOCK","",Settings!$B$7+K9) | S9: =IF(N9="CRITICAL","Order immediately - stock-out before delivery",IF(N9="HIGH","Raise purchase order today",IF(N9="MEDIUM","Plan reorder this week","No action required"))) -> No action required | T9: =IF(I9="IN STOCK",0,IF(N9="CRITICAL",30,IF(N9="HIGH",20,10))+IF(G9>0,(G9-F9)/G9,0)+ROW()/10000000) -> 0 | U9: =IF(T9>0,SUMPRODUCT(--($T$5:$T$104>T9))+1,"")
A10: 45292 | B10: S001 | C10: P0006 | D10: Electronics | E10: North | F10: 305 | G10: 91 | H10: 64.76 | I10: =IF(F10<=G10,"REORDER NOW",IF(F10<=G10*(1+Settings!$B$5),"LOW STOCK","IN STOCK")) -> IN STOCK | J10: =IFERROR(INDEX(Suppliers!$B$5:$B$9,MATCH(D10,Suppliers!$C$5:$C$9,0)),"Unassigned") -> TechSource India | K10: =IFERROR(INDEX(Suppliers!$D$5:$D$9,MATCH(D10,Suppliers!$C$5:$C$9,0)),0) -> 7 | L10: 14.4 | M10: =IF(L10>0,ROUND(F10/L10,1),"") -> 21.2 | N10: =IF(I10="IN STOCK","-",IF(AND(M10<>"",M10<K10),"CRITICAL",IF(I10="REORDER NOW","HIGH","MEDIUM"))) -> - | O10: =IF(I10="IN STOCK",0,MAX(0,ROUNDUP(G10*Settings!$B$6,0)-F10)) -> 0 | P10: =F10*H10 -> 19751.8 | Q10: =O10*H10 -> 0 | R10: =IF(I10="IN STOCK","",Settings!$B$7+K10) | S10: =IF(N10="CRITICAL","Order immediately - stock-out before delivery",IF(N10="HIGH","Raise purchase order today",IF(N10="MEDIUM","Plan reorder this week","No action required"))) -> No action required | T10: =IF(I10="IN STOCK",0,IF(N10="CRITICAL",30,IF(N10="HIGH",20,10))+IF(G10>0,(G10-F10)/G10,0)+ROW()/10000000) -> 0 | U10: =IF(T10>0,SUMPRODUCT(--($T$5:$T$104>T10))+1,"")
A11: 45292 | B11: S001 | C11: P0007 | D11: Clothing | E11: East | F11: 256 | G11: 25 | H11: 77.44 | I11: =IF(F11<=G11,"REORDER NOW",IF(F11<=G11*(1+Settings!$B$5),"LOW STOCK","IN STOCK")) -> IN STOCK | J11: =IFERROR(INDEX(Suppliers!$B$5:$B$9,MATCH(D11,Suppliers!$C$5:$C$9,0)),"Unassigned") -> StyleHub Wholesale | K11: =IFERROR(INDEX(Suppliers!$D$5:$D$9,MATCH(D11,Suppliers!$C$5:$C$9,0)),0) -> 6 | L11: 5.1 | M11: =IF(L11>0,ROUND(F11/L11,1),"") -> 50.2 | N11: =IF(I11="IN STOCK","-",IF(AND(M11<>"",M11<K11),"CRITICAL",IF(I11="REORDER NOW","HIGH","MEDIUM"))) -> - | O11: =IF(I11="IN STOCK",0,MAX(0,ROUNDUP(G11*Settings!$B$6,0)-F11)) -> 0 | P11: =F11*H11 -> 19824.64 | Q11: =O11*H11 -> 0 | R11: =IF(I11="IN STOCK","",Settings!$B$7+K11) | S11: =IF(N11="CRITICAL","Order immediately - stock-out before delivery",IF(N11="HIGH","Raise purchase order today",IF(N11="MEDIUM","Plan reorder this week","No action required"))) -> No action required | T11: =IF(I11="IN STOCK",0,IF(N11="CRITICAL",30,IF(N11="HIGH",20,10))+IF(G11>0,(G11-F11)/G11,0)+ROW()/10000000) -> 0 | U11: =IF(T11>0,SUMPRODUCT(--($T$5:$T$104>T11))+1,"")
A12: 45292 | B12: S001 | C12: P0008 | D12: Electronics | E12: East | F12: 315 | G12: 226 | H12: 31.34 | I12: =IF(F12<=G12,"REORDER NOW",IF(F12<=G12*(1+Settings!$B$5),"LOW STOCK","IN STOCK")) -> IN STOCK | J12: =IFERROR(INDEX(Suppliers!$B$5:$B$9,MATCH(D12,Suppliers!$C$5:$C$9,0)),"Unassigned") -> TechSource India | K12: =IFERROR(INDEX(Suppliers!$D$5:$D$9,MATCH(D12,Suppliers!$C$5:$C$9,0)),0) -> 7 | L12: 24.3 | M12: =IF(L12>0,ROUND(F12/L12,1),"") -> 13 | N12: =IF(I12="IN STOCK","-",IF(AND(M12<>"",M12<K12),"CRITICAL",IF(I12="REORDER NOW","HIGH","MEDIUM"))) -> - | O12: =IF(I12="IN STOCK",0,MAX(0,ROUNDUP(G12*Settings!$B$6,0)-F12)) -> 0 | P12: =F12*H12 -> 9872.1 | Q12: =O12*H12 -> 0 | R12: =IF(I12="IN STOCK","",Settings!$B$7+K12) | S12: =IF(N12="CRITICAL","Order immediately - stock-out before delivery",IF(N12="HIGH","Raise purchase order today",IF(N12="MEDIUM","Plan reorder this week","No action required"))) -> No action required | T12: =IF(I12="IN STOCK",0,IF(N12="CRITICAL",30,IF(N12="HIGH",20,10))+IF(G12>0,(G12-F12)/G12,0)+ROW()/10000000) -> 0 | U12: =IF(T12>0,SUMPRODUCT(--($T$5:$T$104>T12))+1,"")
A13: 45292 | B13: S001 | C13: P0009 | D13: Electronics | E13: South | F13: 167 | G13: 28 | H13: 96.8 | I13: =IF(F13<=G13,"REORDER NOW",IF(F13<=G13*(1+Settings!$B$5),"LOW STOCK","IN STOCK")) -> IN STOCK | J13: =IFERROR(INDEX(Suppliers!$B$5:$B$9,MATCH(D13,Suppliers!$C$5:$C$9,0)),"Unassigned") -> TechSource India | K13: =IFERROR(INDEX(Suppliers!$D$5:$D$9,MATCH(D13,Suppliers!$C$5:$C$9,0)),0) -> 7 | L13: 3.8 | M13: =IF(L13>0,ROUND(F13/L13,1),"") -> 43.9 | N13: =IF(I13="IN STOCK","-",IF(AND(M13<>"",M13<K13),"CRITICAL",IF(I13="REORDER NOW","HIGH","MEDIUM"))) -> - | O13: =IF(I13="IN STOCK",0,MAX(0,ROUNDUP(G13*Settings!$B$6,0)-F13)) -> 0 | P13: =F13*H13 -> 16165.6 | Q13: =O13*H13 -> 0 | R13: =IF(I13="IN STOCK","",Settings!$B$7+K13) | S13: =IF(N13="CRITICAL","Order immediately - stock-out before delivery",IF(N13="HIGH","Raise purchase order today",IF(N13="MEDIUM","Plan reorder this week","No action required"))) -> No action required | T13: =IF(I13="IN STOCK",0,IF(N13="CRITICAL",30,IF(N13="HIGH",20,10))+IF(G13>0,(G13-F13)/G13,0)+ROW()/10000000) -> 0 | U13: =IF(T13>0,SUMPRODUCT(--($T$5:$T$104>T13))+1,"")
A14: 45292 | B14: S001 | C14: P0010 | D14: Furniture | E14: West | F14: 167 | G14: 87 | H14: 40.95 | I14: =IF(F14<=G14,"REORDER NOW",IF(F14<=G14*(1+Settings!$B$5),"LOW STOCK","IN STOCK")) -> IN STOCK | J14: =IFERROR(INDEX(Suppliers!$B$5:$B$9,MATCH(D14,Suppliers!$C$5:$C$9,0)),"Unassigned") -> HomeCraft Suppliers | K14: =IFERROR(INDEX(Suppliers!$D$5:$D$9,MATCH(D14,Suppliers!$C$5:$C$9,0)),0) -> 12 | L14: 5.2 | M14: =IF(L14>0,ROUND(F14/L14,1),"") -> 32.1 | N14: =IF(I14="IN STOCK","-",IF(AND(M14<>"",M14<K14),"CRITICAL",IF(I14="REORDER NOW","HIGH","MEDIUM"))) -> - | O14: =IF(I14="IN STOCK",0,MAX(0,ROUNDUP(G14*Settings!$B$6,0)-F14)) -> 0 | P14: =F14*H14 -> 6838.65 | Q14: =O14*H14 -> 0 | R14: =IF(I14="IN STOCK","",Settings!$B$7+K14) | S14: =IF(N14="CRITICAL","Order immediately - stock-out before delivery",IF(N14="HIGH","Raise purchase order today",IF(N14="MEDIUM","Plan reorder this week","No action required"))) -> No action required | T14: =IF(I14="IN STOCK",0,IF(N14="CRITICAL",30,IF(N14="HIGH",20,10))+IF(G14>0,(G14-F14)/G14,0)+ROW()/10000000) -> 0 | U14: =IF(T14>0,SUMPRODUCT(--($T$5:$T$104>T14))+1,"")
A15: 45292 | B15: S001 | C15: P0011 | D15: Electronics | E15: West | F15: 449 | G15: 33 | H15: 90.89 | I15: =IF(F15<=G15,"REORDER NOW",IF(F15<=G15*(1+Settings!$B$5),"LOW STOCK","IN STOCK")) -> IN STOCK | J15: =IFERROR(INDEX(Suppliers!$B$5:$B$9,MATCH(D15,Suppliers!$C$5:$C$9,0)),"Unassigned") -> TechSource India | K15: =IFERROR(INDEX(Suppliers!$D$5:$D$9,MATCH(D15,Suppliers!$C$5:$C$9,0)),0) -> 7 | L15: 3.9 | M15: =IF(L15>0,ROUND(F15/L15,1),"") -> 115.1 | N15: =IF(I15="IN STOCK","-",IF(AND(M15<>"",M15<K15),"CRITICAL",IF(I15="REORDER NOW","HIGH","MEDIUM"))) -> - | O15: =IF(I15="IN STOCK",0,MAX(0,ROUNDUP(G15*Settings!$B$6,0)-F15)) -> 0 | P15: =F15*H15 -> 40809.61 | Q15: =O15*H15 -> 0 | R15: =IF(I15="IN STOCK","",Settings!$B$7+K15) | S15: =IF(N15="CRITICAL","Order immediately - stock-out before delivery",IF(N15="HIGH","Raise purchase order today",IF(N15="MEDIUM","Plan reorder this week","No action required"))) -> No action required | T15: =IF(I15="IN STOCK",0,IF(N15="CRITICAL",30,IF(N15="HIGH",20,10))+IF(G15>0,(G15-F15)/G15,0)+ROW()/10000000) -> 0 | U15: =IF(T15>0,SUMPRODUCT(--($T$5:$T$104>T15))+1,"")
A16: 45292 | B16: S001 | C16: P0012 | D16: Electronics | E16: East | F16: 213 | G16: 61 | H16: 39.14 | I16: =IF(F16<=G16,"REORDER NOW",IF(F16<=G16*(1+Settings!$B$5),"LOW STOCK","IN STOCK")) -> IN STOCK | J16: =IFERROR(INDEX(Suppliers!$B$5:$B$9,MATCH(D16,Suppliers!$C$5:$C$9,0)),"Unassigned") -> TechSource India | K16: =IFERROR(INDEX(Suppliers!$D$5:$D$9,MATCH(D16,Suppliers!$C$5:$C$9,0)),0) -> 7 | L16: 8.7 | M16: =IF(L16>0,ROUND(F16/L16,1),"") -> 24.5 | N16: =IF(I16="IN STOCK","-",IF(AND(M16<>"",M16<K16),"CRITICAL",IF(I16="REORDER NOW","HIGH","MEDIUM"))) -> - | O16: =IF(I16="IN STOCK",0,MAX(0,ROUNDUP(G16*Settings!$B$6,0)-F16)) -> 0 | P16: =F16*H16 -> 8336.82 | Q16: =O16*H16 -> 0 | R16: =IF(I16="IN STOCK","",Settings!$B$7+K16) | S16: =IF(N16="CRITICAL","Order immediately - stock-out before delivery",IF(N16="HIGH","Raise purchase order today",IF(N16="MEDIUM","Plan reorder this week","No action required"))) -> No action required | T16: =IF(I16="IN STOCK",0,IF(N16="CRITICAL",30,IF(N16="HIGH",20,10))+IF(G16>0,(G16-F16)/G16,0)+ROW()/10000000) -> 0 | U16: =IF(T16>0,SUMPRODUCT(--($T$5:$T$104>T16))+1,"")
... A104: 45292 | B104: S005 | C104: P0020 | D104: Groceries | E104: East | F104: 117 | G104: 2 | H104: 78.39 | I104: =IF(F104<=G104,"REORDER NOW",IF(F104<=G104*(1+Settings!$B$5),"LOW STOCK","IN STOCK")) -> IN STOCK | J104: =IFERROR(INDEX(Suppliers!$B$5:$B$9,MATCH(D104,Suppliers!$C$5:$C$9,0)),"Unassigned") -> FreshLink Traders | K104: =IFERROR(INDEX(Suppliers!$D$5:$D$9,MATCH(D104,Suppliers!$C$5:$C$9,0)),0) -> 2 | L104: 1.2 | M104: =IF(L104>0,ROUND(F104/L104,1),"") -> 97.5 | N104: =IF(I104="IN STOCK","-",IF(AND(M104<>"",M104<K104),"CRITICAL",IF(I104="REORDER NOW","HIGH","MEDIUM"))) -> - | O104: =IF(I104="IN STOCK",0,MAX(0,ROUNDUP(G104*Settings!$B$6,0)-F104)) -> 0 | P104: =F104*H104 -> 9171.63 | Q104: =O104*H104 -> 0 | R104: =IF(I104="IN STOCK","",Settings!$B$7+K104) | S104: =IF(N104="CRITICAL","Order immediately - stock-out before delivery",IF(N104="HIGH","Raise purchase order today",IF(N104="MEDIUM","Plan reorder this week","No action required"))) -> No action required | T104: =IF(I104="IN STOCK",0,IF(N104="CRITICAL",30,IF(N104="HIGH",20,10))+IF(G104>0,(G104-F104)/G104,0)+ROW()/10000000) -> 0 | U104: =IF(T104>0,SUMPRODUCT(--($T$5:$T$104>T104))+1,"")

Sheet Alert_Report
A1: LIVE ALERT REPORT - ITEMS REQUIRING ACTION
A2: ="Items needing action: "&COUNT(Inventory_Data!$U$5:$U$104)&" | Estimated reorder cost: ₹"&TEXT(SUM(Inventory_Data!$Q$5:$Q$104),"#,##0")&" | Sorted automatically: CRITICAL first, then largest shortfall" -> Items needing action: 21 | Estimated reorder cost: ₹477,687 | Sorted automatically: CRITICAL first, then largest shortfall
A4: Rank | B4: Store ID | C4: Product ID | D4: Category | E4: Region | F4: Current Stock | G4: Reorder Level | H4: Stock Status | I4: Priority | J4: Days of Cover | K4: Lead Time (Days) | L4: Supplier | M4: Qty to Order | N4: Est. Cost (₹) | O4: Expected Delivery | P4: Recommended Action
A5: =IF(ROW()-4<=COUNT(Inventory_Data!$U$5:$U$104),ROW()-4,"") -> 1 | B5: =IF($A5="","",INDEX(Inventory_Data!$B$5:$B$104,MATCH($A5,Inventory_Data!$U$5:$U$104,0))) -> S005 | C5: =IF($A5="","",INDEX(Inventory_Data!$C$5:$C$104,MATCH($A5,Inventory_Data!$U$5:$U$104,0))) -> P0003 | D5: =IF($A5="","",INDEX(Inventory_Data!$D$5:$D$104,MATCH($A5,Inventory_Data!$U$5:$U$104,0))) -> Furniture | E5: =IF($A5="","",INDEX(Inventory_Data!$E$5:$E$104,MATCH($A5,Inventory_Data!$U$5:$U$104,0))) -> South | F5: =IF($A5="","",INDEX(Inventory_Data!$F$5:$F$104,MATCH($A5,Inventory_Data!$U$5:$U$104,0))) -> 98 | G5: =IF($A5="","",INDEX(Inventory_Data!$G$5:$G$104,MATCH($A5,Inventory_Data!$U$5:$U$104,0))) -> 106 | H5: =IF($A5="","",INDEX(Inventory_Data!$I$5:$I$104,MATCH($A5,Inventory_Data!$U$5:$U$104,0))) -> REORDER NOW | I5: =IF($A5="","",INDEX(Inventory_Data!$N$5:$N$104,MATCH($A5,Inventory_Data!$U$5:$U$104,0))) -> CRITICAL | J5: =IF($A5="","",INDEX(Inventory_Data!$M$5:$M$104,MATCH($A5,Inventory_Data!$U$5:$U$104,0))) -> 10.5 | K5: =IF($A5="","",INDEX(Inventory_Data!$K$5:$K$104,MATCH($A5,Inventory_Data!$U$5:$U$104,0))) -> 12 | L5: =IF($A5="","",INDEX(Inventory_Data!$J$5:$J$104,MATCH($A5,Inventory_Data!$U$5:$U$104,0))) -> HomeCraft Suppliers | M5: =IF($A5="","",INDEX(Inventory_Data!$O$5:$O$104,MATCH($A5,Inventory_Data!$U$5:$U$104,0))) -> 220 | N5: =IF($A5="","",INDEX(Inventory_Data!$Q$5:$Q$104,MATCH($A5,Inventory_Data!$U$5:$U$104,0))) -> 5317.4 | O5: =IF($A5="","",INDEX(Inventory_Data!$R$5:$R$104,MATCH($A5,Inventory_Data!$U$5:$U$104,0))) -> 45304 | P5: =IF($A5="","",INDEX(Inventory_Data!$S$5:$S$104,MATCH($A5,Inventory_Data!$U$5:$U$104,0))) -> Order immediately - stock-out before delivery
A6: =IF(ROW()-4<=COUNT(Inventory_Data!$U$5:$U$104),ROW()-4,"") -> 2 | B6: =IF($A6="","",INDEX(Inventory_Data!$B$5:$B$104,MATCH($A6,Inventory_Data!$U$5:$U$104,0))) -> S004 | C6: =IF($A6="","",INDEX(Inventory_Data!$C$5:$C$104,MATCH($A6,Inventory_Data!$U$5:$U$104,0))) -> P0002 | D6: =IF($A6="","",INDEX(Inventory_Data!$D$5:$D$104,MATCH($A6,Inventory_Data!$U$5:$U$104,0))) -> Furniture | E6: =IF($A6="","",INDEX(Inventory_Data!$E$5:$E$104,MATCH($A6,Inventory_Data!$U$5:$U$104,0))) -> West | F6: =IF($A6="","",INDEX(Inventory_Data!$F$5:$F$104,MATCH($A6,Inventory_Data!$U$5:$U$104,0))) -> 181 | G6: =IF($A6="","",INDEX(Inventory_Data!$G$5:$G$104,MATCH($A6,Inventory_Data!$U$5:$U$104,0))) -> 193 | H6: =IF($A6="","",INDEX(Inventory_Data!$I$5:$I$104,MATCH($A6,Inventory_Data!$U$5:$U$104,0))) -> REORDER NOW | I6: =IF($A6="","",INDEX(Inventory_Data!$N$5:$N$104,MATCH($A6,Inventory_Data!$U$5:$U$104,0))) -> CRITICAL | J6: =IF($A6="","",INDEX(Inventory_Data!$M$5:$M$104,MATCH($A6,Inventory_Data!$U$5:$U$104,0))) -> 10.4 | K6: =IF($A6="","",INDEX(Inventory_Data!$K$5:$K$104,MATCH($A6,Inventory_Data!$U$5:$U$104,0))) -> 12 | L6: =IF($A6="","",INDEX(Inventory_Data!$J$5:$J$104,MATCH($A6,Inventory_Data!$U$5:$U$104,0))) -> HomeCraft Suppliers | M6: =IF($A6="","",INDEX(Inventory_Data!$O$5:$O$104,MATCH($A6,Inventory_Data!$U$5:$U$104,0))) -> 398 | N6: =IF($A6="","",INDEX(Inventory_Data!$Q$5:$Q$104,MATCH($A6,Inventory_Data!$U$5:$U$104,0))) -> 12198.7 | O6: =IF($A6="","",INDEX(Inventory_Data!$R$5:$R$104,MATCH($A6,Inventory_Data!$U$5:$U$104,0))) -> 45304 | P6: =IF($A6="","",INDEX(Inventory_Data!$S$5:$S$104,MATCH($A6,Inventory_Data!$U$5:$U$104,0))) -> Order immediately - stock-out before delivery
A7: =IF(ROW()-4<=COUNT(Inventory_Data!$U$5:$U$104),ROW()-4,"") -> 3 | B7: =IF($A7="","",INDEX(Inventory_Data!$B$5:$B$104,MATCH($A7,Inventory_Data!$U$5:$U$104,0))) -> S001 | C7: =IF($A7="","",INDEX(Inventory_Data!$C$5:$C$104,MATCH($A7,Inventory_Data!$U$5:$U$104,0))) -> P0019 | D7: =IF($A7="","",INDEX(Inventory_Data!$D$5:$D$104,MATCH($A7,Inventory_Data!$U$5:$U$104,0))) -> Clothing | E7: =IF($A7="","",INDEX(Inventory_Data!$E$5:$E$104,MATCH($A7,Inventory_Data!$U$5:$U$104,0))) -> West | F7: =IF($A7="","",INDEX(Inventory_Data!$F$5:$F$104,MATCH($A7,Inventory_Data!$U$5:$U$104,0))) -> 149 | G7: =IF($A7="","",INDEX(Inventory_Data!$G$5:$G$104,MATCH($A7,Inventory_Data!$U$5:$U$104,0))) -> 155 | H7: =IF($A7="","",INDEX(Inventory_Data!$I$5:$I$104,MATCH($A7,Inventory_Data!$U$5:$U$104,0))) -> REORDER NOW | I7: =IF($A7="","",INDEX(Inventory_Data!$N$5:$N$104,MATCH($A7,Inventory_Data!$U$5:$U$104,0))) -> CRITICAL | J7: =IF($A7="","",INDEX(Inventory_Data!$M$5:$M$104,MATCH($A7,Inventory_Data!$U$5:$U$104,0))) -> 4.9 | K7: =IF($A7="","",INDEX(Inventory_Data!$K$5:$K$104,MATCH($A7,Inventory_Data!$U$5:$U$104,0))) -> 6 | L7: =IF($A7="","",INDEX(Inventory_Data!$J$5:$J$104,MATCH($A7,Inventory_Data!$U$5:$U$104,0))) -> StyleHub Wholesale | M7: =IF($A7="","",INDEX(Inventory_Data!$O$5:$O$104,MATCH($A7,Inventory_Data!$U$5:$U$104,0))) -> 316 | N7: =IF($A7="","",INDEX(Inventory_Data!$Q$5:$Q$104,MATCH($A7,Inventory_Data!$U$5:$U$104,0))) -> 25820.36 | O7: =IF($A7="","",INDEX(Inventory_Data!$R$5:$R$104,MATCH($A7,Inventory_Data!$U$5:$U$104,0))) -> 45298 | P7: =IF($A7="","",INDEX(Inventory_Data!$S$5:$S$104,MATCH($A7,Inventory_Data!$U$5:$U$104,0))) -> Order immediately - stock-out before delivery
A8: =IF(ROW()-4<=COUNT(Inventory_Data!$U$5:$U$104),ROW()-4,"") -> 4 | B8: =IF($A8="","",INDEX(Inventory_Data!$B$5:$B$104,MATCH($A8,Inventory_Data!$U$5:$U$104,0))) -> S004 | C8: =IF($A8="","",INDEX(Inventory_Data!$C$5:$C$104,MATCH($A8,Inventory_Data!$U$5:$U$104,0))) -> P0001 | D8: =IF($A8="","",INDEX(Inventory_Data!$D$5:$D$104,MATCH($A8,Inventory_Data!$U$5:$U$104,0))) -> Electronics | E8: =IF($A8="","",INDEX(Inventory_Data!$E$5:$E$104,MATCH($A8,Inventory_Data!$U$5:$U$104,0))) -> East | F8: =IF($A8="","",INDEX(Inventory_Data!$F$5:$F$104,MATCH($A8,Inventory_Data!$U$5:$U$104,0))) -> 497 | G8: =IF($A8="","",INDEX(Inventory_Data!$G$5:$G$104,MATCH($A8,Inventory_Data!$U$5:$U$104,0))) -> 490 | H8: =IF($A8="","",INDEX(Inventory_Data!$I$5:$I$104,MATCH($A8,Inventory_Data!$U$5:$U$104,0))) -> LOW STOCK | I8: =IF($A8="","",INDEX(Inventory_Data!$N$5:$N$104,MATCH($A8,Inventory_Data!$U$5:$U$104,0))) -> CRITICAL | J8: =IF($A8="","",INDEX(Inventory_Data!$M$5:$M$104,MATCH($A8,Inventory_Data!$U$5:$U$104,0))) -> 5.5 | K8: =IF($A8="","",INDEX(Inventory_Data!$K$5:$K$104,MATCH($A8,Inventory_Data!$U$5:$U$104,0))) -> 7 | L8: =IF($A8="","",INDEX(Inventory_Data!$J$5:$J$104,MATCH($A8,Inventory_Data!$U$5:$U$104,0))) -> TechSource India | M8: =IF($A8="","",INDEX(Inventory_Data!$O$5:$O$104,MATCH($A8,Inventory_Data!$U$5:$U$104,0))) -> 973 | N8: =IF($A8="","",INDEX(Inventory_Data!$Q$5:$Q$104,MATCH($A8,Inventory_Data!$U$5:$U$104,0))) -> 41196.82 | O8: =IF($A8="","",INDEX(Inventory_Data!$R$5:$R$104,MATCH($A8,Inventory_Data!$U$5:$U$104,0))) -> 45299 | P8: =IF($A8="","",INDEX(Inventory_Data!$S$5:$S$104,MATCH($A8,Inventory_Data!$U$5:$U$104,0))) -> Order immediately - stock-out before delivery
A9: =IF(ROW()-4<=COUNT(Inventory_Data!$U$5:$U$104),ROW()-4,"") -> 5 | B9: =IF($A9="","",INDEX(Inventory_Data!$B$5:$B$104,MATCH($A9,Inventory_Data!$U$5:$U$104,0))) -> S002 | C9: =IF($A9="","",INDEX(Inventory_Data!$C$5:$C$104,MATCH($A9,Inventory_Data!$U$5:$U$104,0))) -> P0014 | D9: =IF($A9="","",INDEX(Inventory_Data!$D$5:$D$104,MATCH($A9,Inventory_Data!$U$5:$U$104,0))) -> Clothing | E9: =IF($A9="","",INDEX(Inventory_Data!$E$5:$E$104,MATCH($A9,Inventory_Data!$U$5:$U$104,0))) -> West | F9: =IF($A9="","",INDEX(Inventory_Data!$F$5:$F$104,MATCH($A9,Inventory_Data!$U$5:$U$104,0))) -> 342 | G9: =IF($A9="","",INDEX(Inventory_Data!$G$5:$G$104,MATCH($A9,Inventory_Data!$U$5:$U$104,0))) -> 336 | H9: =IF($A9="","",INDEX(Inventory_Data!$I$5:$I$104,MATCH($A9,Inventory_Data!$U$5:$U$104,0))) -> LOW STOCK | I9: =IF($A9="","",INDEX(Inventory_Data!$N$5:$N$104,MATCH($A9,Inventory_Data!$U$5:$U$104,0))) -> CRITICAL | J9: =IF($A9="","",INDEX(Inventory_Data!$M$5:$M$104,MATCH($A9,Inventory_Data!$U$5:$U$104,0))) -> 4.8 | K9: =IF($A9="","",INDEX(Inventory_Data!$K$5:$K$104,MATCH($A9,Inventory_Data!$U$5:$U$104,0))) -> 6 | L9: =IF($A9="","",INDEX(Inventory_Data!$J$5:$J$104,MATCH($A9,Inventory_Data!$U$5:$U$104,0))) -> StyleHub Wholesale | M9: =IF($A9="","",INDEX(Inventory_Data!$O$5:$O$104,MATCH($A9,Inventory_Data!$U$5:$U$104,0))) -> 666 | N9: =IF($A9="","",INDEX(Inventory_Data!$Q$5:$Q$104,MATCH($A9,Inventory_Data!$U$5:$U$104,0))) -> 46826.46 | O9: =IF($A9="","",INDEX(Inventory_Data!$R$5:$R$104,MATCH($A9,Inventory_Data!$U$5:$U$104,0))) -> 45298 | P9: =IF($A9="","",INDEX(Inventory_Data!$S$5:$S$104,MATCH($A9,Inventory_Data!$U$5:$U$104,0))) -> Order immediately - stock-out before delivery
A10: =IF(ROW()-4<=COUNT(Inventory_Data!$U$5:$U$104),ROW()-4,"") -> 6 | B10: =IF($A10="","",INDEX(Inventory_Data!$B$5:$B$104,MATCH($A10,Inventory_Data!$U$5:$U$104,0))) -> S001 | C10: =IF($A10="","",INDEX(Inventory_Data!$C$5:$C$104,MATCH($A10,Inventory_Data!$U$5:$U$104,0))) -> P0003 | D10: =IF($A10="","",INDEX(Inventory_Data!$D$5:$D$104,MATCH($A10,Inventory_Data!$U$5:$U$104,0))) -> Toys | E10: =IF($A10="","",INDEX(Inventory_Data!$E$5:$E$104,MATCH($A10,Inventory_Data!$U$5:$U$104,0))) -> East | F10: =IF($A10="","",INDEX(Inventory_Data!$F$5:$F$104,MATCH($A10,Inventory_Data!$U$5:$U$104,0))) -> 69 | G10: =IF($A10="","",INDEX(Inventory_Data!$G$5:$G$104,MATCH($A10,Inventory_Data!$U$5:$U$104,0))) -> 77 | H10: =IF($A10="","",INDEX(Inventory_Data!$I$5:$I$104,MATCH($A10,Inventory_Data!$U$5:$U$104,0))) -> REORDER NOW | I10: =IF($A10="","",INDEX(Inventory_Data!$N$5:$N$104,MATCH($A10,Inventory_Data!$U$5:$U$104,0))) -> HIGH | J10: =IF($A10="","",INDEX(Inventory_Data!$M$5:$M$104,MATCH($A10,Inventory_Data!$U$5:$U$104,0))) -> 5.2 | K10: =IF($A10="","",INDEX(Inventory_Data!$K$5:$K$104,MATCH($A10,Inventory_Data!$U$5:$U$104,0))) -> 5 | L10: =IF($A10="","",INDEX(Inventory_Data!$J$5:$J$104,MATCH($A10,Inventory_Data!$U$5:$U$104,0))) -> PlayWorld Distributors | M10: =IF($A10="","",INDEX(Inventory_Data!$O$5:$O$104,MATCH($A10,Inventory_Data!$U$5:$U$104,0))) -> 162 | N10: =IF($A10="","",INDEX(Inventory_Data!$Q$5:$Q$104,MATCH($A10,Inventory_Data!$U$5:$U$104,0))) -> 3554.28 | O10: =IF($A10="","",INDEX(Inventory_Data!$R$5:$R$104,MATCH($A10,Inventory_Data!$U$5:$U$104,0))) -> 45297 | P10: =IF($A10="","",INDEX(Inventory_Data!$S$5:$S$104,MATCH($A10,Inventory_Data!$U$5:$U$104,0))) -> Raise purchase order today
A11: =IF(ROW()-4<=COUNT(Inventory_Data!$U$5:$U$104),ROW()-4,"") -> 7 | B11: =IF($A11="","",INDEX(Inventory_Data!$B$5:$B$104,MATCH($A11,Inventory_Data!$U$5:$U$104,0))) -> S003 | C11: =IF($A11="","",INDEX(Inventory_Data!$C$5:$C$104,MATCH($A11,Inventory_Data!$U$5:$U$104,0))) -> P0007 | D11: =IF($A11="","",INDEX(Inventory_Data!$D$5:$D$104,MATCH($A11,Inventory_Data!$U$5:$U$104,0))) -> Electronics | E11: =IF($A11="","",INDEX(Inventory_Data!$E$5:$E$104,MATCH($A11,Inventory_Data!$U$5:$U$104,0))) -> North | F11: =IF($A11="","",INDEX(Inventory_Data!$F$5:$F$104,MATCH($A11,Inventory_Data!$U$5:$U$104,0))) -> 108 | G11: =IF($A11="","",INDEX(Inventory_Data!$G$5:$G$104,MATCH($A11,Inventory_Data!$U$5:$U$104,0))) -> 109 | H11: =IF($A11="","",INDEX(Inventory_Data!$I$5:$I$104,MATCH($A11,Inventory_Data!$U$5:$U$104,0))) -> REORDER NOW | I11: =IF($A11="","",INDEX(Inventory_Data!$N$5:$N$104,MATCH($A11,Inventory_Data!$U$5:$U$104,0))) -> HIGH | J11: =IF($A11="","",INDEX(Inventory_Data!$M$5:$M$104,MATCH($A11,Inventory_Data!$U$5:$U$104,0))) -> 9.2 | K11: =IF($A11="","",INDEX(Inventory_Data!$K$5:$K$104,MATCH($A11,Inventory_Data!$U$5:$U$104,0))) -> 7 | L11: =IF($A11="","",INDEX(Inventory_Data!$J$5:$J$104,MATCH($A11,Inventory_Data!$U$5:$U$104,0))) -> TechSource India | M11: =IF($A11="","",INDEX(Inventory_Data!$O$5:$O$104,MATCH($A11,Inventory_Data!$U$5:$U$104,0))) -> 219 | N11: =IF($A11="","",INDEX(Inventory_Data!$Q$5:$Q$104,MATCH($A11,Inventory_Data!$U$5:$U$104,0))) -> 12016.53 | O11: =IF($A11="","",INDEX(Inventory_Data!$R$5:$R$104,MATCH($A11,Inventory_Data!$U$5:$U$104,0))) -> 45299 | P11: =IF($A11="","",INDEX(Inventory_Data!$S$5:$S$104,MATCH($A11,Inventory_Data!$U$5:$U$104,0))) -> Raise purchase order today
A12: =IF(ROW()-4<=COUNT(Inventory_Data!$U$5:$U$104),ROW()-4,"") -> 8 | B12: =IF($A12="","",INDEX(Inventory_Data!$B$5:$B$104,MATCH($A12,Inventory_Data!$U$5:$U$104,0))) -> S004 | C12: =IF($A12="","",INDEX(Inventory_Data!$C$5:$C$104,MATCH($A12,Inventory_Data!$U$5:$U$104,0))) -> P0020 | D12: =IF($A12="","",INDEX(Inventory_Data!$D$5:$D$104,MATCH($A12,Inventory_Data!$U$5:$U$104,0))) -> Toys | E12: =IF($A12="","",INDEX(Inventory_Data!$E$5:$E$104,MATCH($A12,Inventory_Data!$U$5:$U$104,0))) -> West | F12: =IF($A12="","",INDEX(Inventory_Data!$F$5:$F$104,MATCH($A12,Inventory_Data!$U$5:$U$104,0))) -> 249 | G12: =IF($A12="","",INDEX(Inventory_Data!$G$5:$G$104,MATCH($A12,Inventory_Data!$U$5:$U$104,0))) -> 248 | H12: =IF($A12="","",INDEX(Inventory_Data!$I$5:$I$104,MATCH($A12,Inventory_Data!$U$5:$U$104,0))) -> LOW STOCK | I12: =IF($A12="","",INDEX(Inventory_Data!$N$5:$N$104,MATCH($A12,Inventory_Data!$U$5:$U$104,0))) -> MEDIUM | J12: =IF($A12="","",INDEX(Inventory_Data!$M$5:$M$104,MATCH($A12,Inventory_Data!$U$5:$U$104,0))) -> 5.9 | K12: =IF($A12="","",INDEX(Inventory_Data!$K$5:$K$104,MATCH($A12,Inventory_Data!$U$5:$U$104,0))) -> 5 | L12: =IF($A12="","",INDEX(Inventory_Data!$J$5:$J$104,MATCH($A12,Inventory_Data!$U$5:$U$104,0))) -> PlayWorld Distributors | M12: =IF($A12="","",INDEX(Inventory_Data!$O$5:$O$104,MATCH($A12,Inventory_Data!$U$5:$U$104,0))) -> 495 | N12: =IF($A12="","",INDEX(Inventory_Data!$Q$5:$Q$104,MATCH($A12,Inventory_Data!$U$5:$U$104,0))) -> 16270.65 | O12: =IF($A12="","",INDEX(Inventory_Data!$R$5:$R$104,MATCH($A12,Inventory_Data!$U$5:$U$104,0))) -> 45297 | P12: =IF($A12="","",INDEX(Inventory_Data!$S$5:$S$104,MATCH($A12,Inventory_Data!$U$5:$U$104,0))) -> Plan reorder this week
A13: =IF(ROW()-4<=COUNT(Inventory_Data!$U$5:$U$104),ROW()-4,"") -> 9 | B13: =IF($A13="","",INDEX(Inventory_Data!$B$5:$B$104,MATCH($A13,Inventory_Data!$U$5:$U$104,0))) -> S003 | C13: =IF($A13="","",INDEX(Inventory_Data!$C$5:$C$104,MATCH($A13,Inventory_Data!$U$5:$U$104,0))) -> P0010 | D13: =IF($A13="","",INDEX(Inventory_Data!$D$5:$D$104,MATCH($A13,Inventory_Data!$U$5:$U$104,0))) -> Furniture | E13: =IF($A13="","",INDEX(Inventory_Data!$E$5:$E$104,MATCH($A13,Inventory_Data!$U$5:$U$104,0))) -> East | F13: =IF($A13="","",INDEX(Inventory_Data!$F$5:$F$104,MATCH($A13,Inventory_Data!$U$5:$U$104,0))) -> 413 | G13: =IF($A13="","",INDEX(Inventory_Data!$G$5:$G$104,MATCH($A13,Inventory_Data!$U$5:$U$104,0))) -> 409 | H13: =IF($A13="","",INDEX(Inventory_Data!$I$5:$I$104,MATCH($A13,Inventory_Data!$U$5:$U$104,0))) -> LOW STOCK | I13: =IF($A13="","",INDEX(Inventory_Data!$N$5:$N$104,MATCH($A13,Inventory_Data!$U$5:$U$104,0))) -> MEDIUM | J13: =IF($A13="","",INDEX(Inventory_Data!$M$5:$M$104,MATCH($A13,Inventory_Data!$U$5:$U$104,0))) -> 13.2 | K13: =IF($A13="","",INDEX(Inventory_Data!$K$5:$K$104,MATCH($A13,Inventory_Data!$U$5:$U$104,0))) -> 12 | L13: =IF($A13="","",INDEX(Inventory_Data!$J$5:$J$104,MATCH($A13,Inventory_Data!$U$5:$U$104,0))) -> HomeCraft Suppliers | M13: =IF($A13="","",INDEX(Inventory_Data!$O$5:$O$104,MATCH($A13,Inventory_Data!$U$5:$U$104,0))) -> 814 | N13: =IF($A13="","",INDEX(Inventory_Data!$Q$5:$Q$104,MATCH($A13,Inventory_Data!$U$5:$U$104,0))) -> 65828.18 | O13: =IF($A13="","",INDEX(Inventory_Data!$R$5:$R$104,MATCH($A13,Inventory_Data!$U$5:$U$104,0))) -> 45304 | P13: =IF($A13="","",INDEX(Inventory_Data!$S$5:$S$104,MATCH($A13,Inventory_Data!$U$5:$U$104,0))) -> Plan reorder this week
A14: =IF(ROW()-4<=COUNT(Inventory_Data!$U$5:$U$104),ROW()-4,"") -> 10 | B14: =IF($A14="","",INDEX(Inventory_Data!$B$5:$B$104,MATCH($A14,Inventory_Data!$U$5:$U$104,0))) -> S004 | C14: =IF($A14="","",INDEX(Inventory_Data!$C$5:$C$104,MATCH($A14,Inventory_Data!$U$5:$U$104,0))) -> P0008 | D14: =IF($A14="","",INDEX(Inventory_Data!$D$5:$D$104,MATCH($A14,Inventory_Data!$U$5:$U$104,0))) -> Furniture | E14: =IF($A14="","",INDEX(Inventory_Data!$E$5:$E$104,MATCH($A14,Inventory_Data!$U$5:$U$104,0))) -> West | F14: =IF($A14="","",INDEX(Inventory_Data!$F$5:$F$104,MATCH($A14,Inventory_Data!$U$5:$U$104,0))) -> 390 | G14: =IF($A14="","",INDEX(Inventory_Data!$G$5:$G$104,MATCH($A14,Inventory_Data!$U$5:$U$104,0))) -> 369 | H14: =IF($A14="","",INDEX(Inventory_Data!$I$5:$I$104,MATCH($A14,Inventory_Data!$U$5:$U$104,0))) -> LOW STOCK | I14: =IF($A14="","",INDEX(Inventory_Data!$N$5:$N$104,MATCH($A14,Inventory_Data!$U$5:$U$104,0))) -> MEDIUM | J14: =IF($A14="","",INDEX(Inventory_Data!$M$5:$M$104,MATCH($A14,Inventory_Data!$U$5:$U$104,0))) -> 17.6 | K14: =IF($A14="","",INDEX(Inventory_Data!$K$5:$K$104,MATCH($A14,Inventory_Data!$U$5:$U$104,0))) -> 12 | L14: =IF($A14="","",INDEX(Inventory_Data!$J$5:$J$104,MATCH($A14,Inventory_Data!$U$5:$U$104,0))) -> HomeCraft Suppliers | M14: =IF($A14="","",INDEX(Inventory_Data!$O$5:$O$104,MATCH($A14,Inventory_Data!$U$5:$U$104,0))) -> 717 | N14: =IF($A14="","",INDEX(Inventory_Data!$Q$5:$Q$104,MATCH($A14,Inventory_Data!$U$5:$U$104,0))) -> 57833.22 | O14: =IF($A14="","",INDEX(Inventory_Data!$R$5:$R$104,MATCH($A14,Inventory_Data!$U$5:$U$104,0))) -> 45304 | P14: =IF($A14="","",INDEX(Inventory_Data!$S$5:$S$104,MATCH($A14,Inventory_Data!$U$5:$U$104,0))) -> Plan reorder this week
A15: =IF(ROW()-4<=COUNT(Inventory_Data!$U$5:$U$104),ROW()-4,"") -> 11 | B15: =IF($A15="","",INDEX(Inventory_Data!$B$5:$B$104,MATCH($A15,Inventory_Data!$U$5:$U$104,0))) -> S002 | C15: =IF($A15="","",INDEX(Inventory_Data!$C$5:$C$104,MATCH($A15,Inventory_Data!$U$5:$U$104,0))) -> P0006 | D15: =IF($A15="","",INDEX(Inventory_Data!$D$5:$D$104,MATCH($A15,Inventory_Data!$U$5:$U$104,0))) -> Toys | E15: =IF($A15="","",INDEX(Inventory_Data!$E$5:$E$104,MATCH($A15,Inventory_Data!$U$5:$U$104,0))) -> East | F15: =IF($A15="","",INDEX(Inventory_Data!$F$5:$F$104,MATCH($A15,Inventory_Data!$U$5:$U$104,0))) -> 160 | G15: =IF($A15="","",INDEX(Inventory_Data!$G$5:$G$104,MATCH($A15,Inventory_Data!$U$5:$U$104,0))) -> 151 | H15: =IF($A15="","",INDEX(Inventory_Data!$I$5:$I$104,MATCH($A15,Inventory_Data!$U$5:$U$104,0))) -> LOW STOCK | I15: =IF($A15="","",INDEX(Inventory_Data!$N$5:$N$104,MATCH($A15,Inventory_Data!$U$5:$U$104,0))) -> MEDIUM | J15: =IF($A15="","",INDEX(Inventory_Data!$M$5:$M$104,MATCH($A15,Inventory_Data!$U$5:$U$104,0))) -> 5.9 | K15: =IF($A15="","",INDEX(Inventory_Data!$K$5:$K$104,MATCH($A15,Inventory_Data!$U$5:$U$104,0))) -> 5 | L15: =IF($A15="","",INDEX(Inventory_Data!$J$5:$J$104,MATCH($A15,Inventory_Data!$U$5:$U$104,0))) -> PlayWorld Distributors | M15: =IF($A15="","",INDEX(Inventory_Data!$O$5:$O$104,MATCH($A15,Inventory_Data!$U$5:$U$104,0))) -> 293 | N15: =IF($A15="","",INDEX(Inventory_Data!$Q$5:$Q$104,MATCH($A15,Inventory_Data!$U$5:$U$104,0))) -> 5584.58 | O15: =IF($A15="","",INDEX(Inventory_Data!$R$5:$R$104,MATCH($A15,Inventory_Data!$U$5:$U$104,0))) -> 45297 | P15: =IF($A15="","",INDEX(Inventory_Data!$S$5:$S$104,MATCH($A15,Inventory_Data!$U$5:$U$104,0))) -> Plan reorder this week
A16: =IF(ROW()-4<=COUNT(Inventory_Data!$U$5:$U$104),ROW()-4,"") -> 12 | B16: =IF($A16="","",INDEX(Inventory_Data!$B$5:$B$104,MATCH($A16,Inventory_Data!$U$5:$U$104,0))) -> S003 | C16: =IF($A16="","",INDEX(Inventory_Data!$C$5:$C$104,MATCH($A16,Inventory_Data!$U$5:$U$104,0))) -> P0012 | D16: =IF($A16="","",INDEX(Inventory_Data!$D$5:$D$104,MATCH($A16,Inventory_Data!$U$5:$U$104,0))) -> Clothing | E16: =IF($A16="","",INDEX(Inventory_Data!$E$5:$E$104,MATCH($A16,Inventory_Data!$U$5:$U$104,0))) -> North | F16: =IF($A16="","",INDEX(Inventory_Data!$F$5:$F$104,MATCH($A16,Inventory_Data!$U$5:$U$104,0))) -> 108 | G16: =IF($A16="","",INDEX(Inventory_Data!$G$5:$G$104,MATCH($A16,Inventory_Data!$U$5:$U$104,0))) -> 101 | H16: =IF($A16="","",INDEX(Inventory_Data!$I$5:$I$104,MATCH($A16,Inventory_Data!$U$5:$U$104,0))) -> LOW STOCK | I16: =IF($A16="","",INDEX(Inventory_Data!$N$5:$N$104,MATCH($A16,Inventory_Data!$U$5:$U$104,0))) -> MEDIUM | J16: =IF($A16="","",INDEX(Inventory_Data!$M$5:$M$104,MATCH($A16,Inventory_Data!$U$5:$U$104,0))) -> 7.8 | K16: =IF($A16="","",INDEX(Inventory_Data!$K$5:$K$104,MATCH($A16,Inventory_Data!$U$5:$U$104,0))) -> 6 | L16: =IF($A16="","",INDEX(Inventory_Data!$J$5:$J$104,MATCH($A16,Inventory_Data!$U$5:$U$104,0))) -> StyleHub Wholesale | M16: =IF($A16="","",INDEX(Inventory_Data!$O$5:$O$104,MATCH($A16,Inventory_Data!$U$5:$U$104,0))) -> 195 | N16: =IF($A16="","",INDEX(Inventory_Data!$Q$5:$Q$104,MATCH($A16,Inventory_Data!$U$5:$U$104,0))) -> 16489.2 | O16: =IF($A16="","",INDEX(Inventory_Data!$R$5:$R$104,MATCH($A16,Inventory_Data!$U$5:$U$104,0))) -> 45298 | P16: =IF($A16="","",INDEX(Inventory_Data!$S$5:$S$104,MATCH($A16,Inventory_Data!$U$5:$U$104,0))) -> Plan reorder this week
... A104: =IF(ROW()-4<=COUNT(Inventory_Data!$U$5:$U$104),ROW()-4,"") | B104: =IF($A104="","",INDEX(Inventory_Data!$B$5:$B$104,MATCH($A104,Inventory_Data!$U$5:$U$104,0))) | C104: =IF($A104="","",INDEX(Inventory_Data!$C$5:$C$104,MATCH($A104,Inventory_Data!$U$5:$U$104,0))) | D104: =IF($A104="","",INDEX(Inventory_Data!$D$5:$D$104,MATCH($A104,Inventory_Data!$U$5:$U$104,0))) | E104: =IF($A104="","",INDEX(Inventory_Data!$E$5:$E$104,MATCH($A104,Inventory_Data!$U$5:$U$104,0))) | F104: =IF($A104="","",INDEX(Inventory_Data!$F$5:$F$104,MATCH($A104,Inventory_Data!$U$5:$U$104,0))) | G104: =IF($A104="","",INDEX(Inventory_Data!$G$5:$G$104,MATCH($A104,Inventory_Data!$U$5:$U$104,0))) | H104: =IF($A104="","",INDEX(Inventory_Data!$I$5:$I$104,MATCH($A104,Inventory_Data!$U$5:$U$104,0))) | I104: =IF($A104="","",INDEX(Inventory_Data!$N$5:$N$104,MATCH($A104,Inventory_Data!$U$5:$U$104,0))) | J104: =IF($A104="","",INDEX(Inventory_Data!$M$5:$M$104,MATCH($A104,Inventory_Data!$U$5:$U$104,0))) | K104: =IF($A104="","",INDEX(Inventory_Data!$K$5:$K$104,MATCH($A104,Inventory_Data!$U$5:$U$104,0))) | L104: =IF($A104="","",INDEX(Inventory_Data!$J$5:$J$104,MATCH($A104,Inventory_Data!$U$5:$U$104,0))) | M104: =IF($A104="","",INDEX(Inventory_Data!$O$5:$O$104,MATCH($A104,Inventory_Data!$U$5:$U$104,0))) | N104: =IF($A104="","",INDEX(Inventory_Data!$Q$5:$Q$104,MATCH($A104,Inventory_Data!$U$5:$U$104,0))) | O104: =IF($A104="","",INDEX(Inventory_Data!$R$5:$R$104,MATCH($A104,Inventory_Data!$U$5:$U$104,0))) | P104: =IF($A104="","",INDEX(Inventory_Data!$S$5:$S$104,MATCH($A104,Inventory_Data!$U$5:$U$104,0)))

Sheet Stock_Lookup
A1: STOCK CHECK - SEARCH ANY ITEM
A2: Pick a Store and Product ID from the dropdowns (yellow cells) to see its live stock alert.
A4: Store ID | B4: S001 | D4: =IF($B$6=0,"NOT FOUND",INDEX(Inventory_Data!$I$5:$I$104,$B$6)) -> REORDER NOW
A5: Product ID | B5: P0003
A6: Record # (auto) | B6: =SUMPRODUCT((Inventory_Data!$B$5:$B$104=$B$4)*(Inventory_Data!$C$5:$C$104=$B$5)*(ROW(Inventory_Data!$B$5:$B$104)-4)) -> 3
A8: Field | B8: Value
A9: Category | B9: =IF($B$6=0,"-",INDEX(Inventory_Data!$D$5:$D$104,$B$6)) -> Toys
A10: Region | B10: =IF($B$6=0,"-",INDEX(Inventory_Data!$E$5:$E$104,$B$6)) -> East
A11: Current Stock | B11: =IF($B$6=0,"-",INDEX(Inventory_Data!$F$5:$F$104,$B$6)) -> 69
A12: Reorder Level | B12: =IF($B$6=0,"-",INDEX(Inventory_Data!$G$5:$G$104,$B$6)) -> 77
A13: Unit Price (₹) | B13: =IF($B$6=0,"-",INDEX(Inventory_Data!$H$5:$H$104,$B$6)) -> 21.94
A14: Stock Status | B14: =IF($B$6=0,"-",INDEX(Inventory_Data!$I$5:$I$104,$B$6)) -> REORDER NOW
A15: Priority | B15: =IF($B$6=0,"-",INDEX(Inventory_Data!$N$5:$N$104,$B$6)) -> HIGH
A16: Supplier | B16: =IF($B$6=0,"-",INDEX(Inventory_Data!$J$5:$J$104,$B$6)) -> PlayWorld Distributors
A17: Lead Time (Days) | B17: =IF($B$6=0,"-",INDEX(Inventory_Data!$K$5:$K$104,$B$6)) -> 5
A18: Avg Daily Sales (Units) | B18: =IF($B$6=0,"-",INDEX(Inventory_Data!$L$5:$L$104,$B$6)) -> 13.3
A19: Days of Cover | B19: =IF($B$6=0,"-",INDEX(Inventory_Data!$M$5:$M$104,$B$6)) -> 5.2
A20: Suggested Reorder Qty | B20: =IF($B$6=0,"-",INDEX(Inventory_Data!$O$5:$O$104,$B$6)) -> 162
A21: Estimated Reorder Cost (₹) | B21: =IF($B$6=0,"-",INDEX(Inventory_Data!$Q$5:$Q$104,$B$6)) -> 3554.28
A22: Expected Delivery | B22: =IF($B$6=0,"-",INDEX(Inventory_Data!$R$5:$R$104,$B$6)) -> 45297
A23: Recommended Action | B23: =IF($B$6=0,"-",INDEX(Inventory_Data!$S$5:$S$104,$B$6)) -> Raise purchase order today

Sheet Suppliers
A1: SUPPLIER MASTER
A2: Illustrative supplier data added for the working model (not from Kaggle). Edit blue cells to match real suppliers.
A4: Supplier ID | B4: Supplier Name | C4: Category Supplied | D4: Lead Time (Days) | E4: Reliability Rating (%) | F4: City | G4: Contact (sample)
A5: SUP01 | B5: StyleHub Wholesale | C5: Clothing | D5: 6 | E5: 92 | F5: Tiruppur | G5: orders@stylehub.example
A6: SUP02 | B6: TechSource India | C6: Electronics | D6: 7 | E6: 95 | F6: Chennai | G6: supply@techsource.example
A7: SUP03 | B7: HomeCraft Suppliers | C7: Furniture | D7: 12 | E7: 88 | F7: Coimbatore | G7: po@homecraft.example
A8: SUP04 | B8: FreshLink Traders | C8: Groceries | D8: 2 | E8: 97 | F8: Madurai | G8: dispatch@freshlink.example
A9: SUP05 | B9: PlayWorld Distributors | C9: Toys | D9: 5 | E9: 90 | F9: Bengaluru | G9: sales@playworld.example
A11: Lead Time and Reliability are assumed values for modelling. Each category is mapped to one supplier; the Inventory_Data sheet looks the supplier up automatically.

Sheet Settings
A1: CONTROL PANEL - ALERT RULES & LISTS
A2: Blue text on yellow = editable input. Change a value and every sheet recalculates automatically.
A4: Parameter | B4: Value | C4: Description | E4: Store List | F4: Category List | G4: Product ID List
A5: Low Stock Buffer (%) | B5: 0.25 | C5: Stock above Reorder Level but within this % of it is flagged LOW STOCK (early warning). | E5: All | F5: All | G5: P0001
A6: Order-Up-To Multiple (x Reorder Level) | B6: 3 | C6: Target stock after replenishment = Reorder Level x this multiple. Used for Suggested Reorder Qty. | E6: S001 | F6: Clothing | G6: P0002
A7: Report Date | B7: =MAX(Inventory_Data!$A$5:$A$104) -> 45292 | C7: Latest inventory date in the data. Expected Delivery = Report Date + supplier lead time. | E7: S002 | F7: Electronics | G7: P0003
E8: S003 | F8: Furniture | G8: P0004
A9: Auto helper cells (do not edit) | E9: S004 | F9: Groceries | G9: P0005
A10: Dashboard store filter criterion | B10: =IF(Dashboard!$B$4="All","*",Dashboard!$B$4) -> * | C10: "*" = match everything when the filter is set to All. | E10: S005 | F10: Toys | G10: P0006
A11: Dashboard category filter criterion | B11: =IF(Dashboard!$E$4="All","*",Dashboard!$E$4) -> * | G11: P0007
G12: P0008
G13: P0009
G14: P0010
G15: P0011
G16: P0012
G17: P0013
G18: P0014
G19: P0015
G20: P0016
G21: P0017
G22: P0018
G23: P0019
G24: P0020

Sheet Data_Dictionary
A1: DATA DICTIONARY
A3: Column | B3: Meaning | C3: Source / Rule | D3: Data Type
A4: Date | B4: Inventory record date | C4: Kaggle source | D4: Date
A5: Store ID | B5: Store identifier | C5: Kaggle source | D5: Text
A6: Product ID | B6: Product identifier | C6: Kaggle source | D6: Text
A7: Category | B7: Product category | C7: Kaggle source | D7: Text
A8: Region | B8: Store region | C8: Kaggle source | D8: Text
A9: Current Stock | B9: Units currently available | C9: Kaggle: Inventory Level | D9: Number
A10: Reorder Level | B10: Stock threshold used for alerting | C10: Derived from Demand Forecast (rounded) | D10: Number
A11: Unit Price (₹) | B11: Price per unit | C11: Kaggle: Price | D11: Currency
A12: Stock Status | B12: Inventory alert category | C12: Formula: REORDER NOW if Stock <= Reorder Level; LOW STOCK if within buffer %; else IN STOCK | D12: Formula/Text
A13: Supplier | B13: Supplier mapped to the product category | C13: Lookup from Suppliers sheet | D13: Formula/Text
A14: Lead Time (Days) | B14: Days the supplier takes to deliver | C14: Lookup from Suppliers sheet (assumed) | D14: Formula/Number
... A24: Alert Rank (helper) | B24: Rank of the alert (1 = most urgent) | C24: SUMPRODUCT rank on Priority Score | D24: Formula/Number

Sheet Source_Notes
A1: SOURCE & DATA PREPARATION NOTES
A3: Original file | B3: retail_store_inventory.csv
A4: Original records | B4: 73,100
A5: Original fields | B5: 15
A6: Date range | B6: 01-Jan-2022 to 01-Jan-2024
A7: Working snapshot | B7: 100 records from 01-Jan-2024
A8: Why snapshot? | B8: A single latest-date snapshot keeps the working model focused on current inventory rather than mixing historical records.
A9: Reorder Level | B9: Not present in source. Demand Forecast is used as the derived threshold and is clearly documented so the model is transparent.
A10: Data integrity | B10: No source values were invented. Only the working-model Reorder Level was derived from the source Demand Forecast field.
A11: Extra data added | B11: Suppliers (names, lead times, reliability) and Avg Daily Sales were added as illustrative modelling assumptions. They are NOT from the Kaggle dataset and are shown in blue so they can be replaced with real data.

Sheet Formulas_Used
A1: FORMULAS & FUNCTIONS USED IN THIS MODEL
A2: Every formula below is live in the workbook. Examples show the formula as written for the first data row.
A4: # | B4: Function / Feature | C4: Where Used | D4: Purpose | E4: Example Formula | F4: How It Works
A5: 1 | B5: IF (nested) | C5: Inventory_Data!I (Stock Status) | D5: Classify each item as REORDER NOW / LOW STOCK / IN STOCK | E5: =IF(F5<=G5,"REORDER NOW",IF(F5<=G5*(1+Settings!$B$5),"LOW STOCK","IN STOCK")) | F5: Checks stock against the reorder level first; if not below it, checks whether it is within the buffer % above it; otherwise the item is healthy.
A6: 2 | B6: INDEX + MATCH | C6: Inventory_Data!J,K; Alert_Report; Dashboard Top 10; Stock_Lookup | D6: Look up a value from another table/row | E6: =IFERROR(INDEX(Suppliers!$B$5:$B$9,MATCH(D5,Suppliers!$C$5:$C$9,0)),"Unassigned") | F6: MATCH finds the position of the category in the supplier list; INDEX returns the supplier name at that position.
A7: 3 | B7: IFERROR | C7: Lookups throughout | D7: Show a clean fallback instead of an error | E7: =IFERROR(INDEX(...),"Unassigned") | F7: If the lookup fails (e.g. category missing), the fallback value appears instead of an error value.
A8: 4 | B8: ROUND | C8: Inventory_Data!M (Days of Cover) | D8: Round days of cover to 1 decimal | E8: =IF(L5>0,ROUND(F5/L5,1),"") | F8: Divides stock by average daily sales to get how many days stock lasts; guards against divide-by-zero.
A9: 5 | B9: AND + IF | C9: Inventory_Data!N (Priority) | D9: Assign urgency level | E9: =IF(I5="IN STOCK","-",IF(AND(M5<>"",M5<K5),"CRITICAL",IF(I5="REORDER NOW","HIGH","MEDIUM"))) | F9: CRITICAL when stock will run out before the supplier can deliver (cover < lead time).
A10: 6 | B10: MAX + ROUNDUP | C10: Inventory_Data!O (Suggested Reorder Qty) | D10: Compute units to order | E10: =IF(I5="IN STOCK",0,MAX(0,ROUNDUP(G5*Settings!$B$6,0)-F5)) | F10: Order-up-to level (reorder level x multiple) minus current stock; never negative.
A11: 7 | B11: Arithmetic (*, +) | C11: Inventory_Data!P,Q,R | D11: Stock value, reorder cost, expected delivery date | E11: =F5*H5 | =Settings!$B$7+K5 | F11: Quantity x price for values; report date + lead time days for the delivery date.
A12: 8 | B12: MAX (date) | C12: Settings!B7 (Report Date) | D12: Find the latest inventory date | E12: =MAX(Inventory_Data!$A$5:$A$104) | F12: Returns the most recent date in the data; used as "today" for the model.
A13: 9 | B13: ROW | C13: Inventory_Data!T; Alert_Report!A | D13: Row number as a unique tiebreaker / counter | E13: =...+ROW()/10000000 | F13: Adds a tiny unique number so two items with equal scores still get different ranks.
A14: 10 | B14: SUMPRODUCT | C14: Inventory_Data!U (Alert Rank); Stock_Lookup!B6 | D14: Rank alerts; find a record by two keys (Store + Product) | E14: =IF(T5>0,SUMPRODUCT(--($T$5:$T$104>T5))+1,"") | F14: Counts how many items have a higher score, so rank = that count + 1 (1 = most urgent).
A15: 11 | B15: COUNT | C15: Alert_Report!A and A2 | D15: Count how many alerts exist | E15: =IF(ROW()-4<=COUNT(Inventory_Data!$U$5:$U$104),ROW()-4,"") | F15: Only as many report rows are filled as there are alerts; remaining rows stay blank.
A16: 12 | B16: COUNTIFS | C16: Dashboard KPI cards & breakdown tables | D16: Count items by status, store, category, region | E16: =COUNTIFS(Inventory_Data!$B$5:$B$104,$A30,Inventory_Data!$I$5:$I$104,B$29) | F16: Counts rows meeting all conditions at once.
... A24: 20 | B24: Charts | C24: Dashboard | D24: Visualise status by store, category and overall | E24: Linked to Dashboard breakdown tables | F24: Charts refresh automatically as formulas recalculate.
A26: STATUS LOGIC AT A GLANCE
A27: REORDER NOW : Current Stock <= Reorder Level
A28: LOW STOCK : Reorder Level < Current Stock <= Reorder Level x (1 + Low Stock Buffer %)
A29: IN STOCK : Current Stock above the buffer zone
A30: CRITICAL : Alert item whose Days of Cover < Supplier Lead Time (will run out before new stock arrives)
A32: HOW TO UPDATE THE MODEL
A33: 1. Paste new Current Stock / Reorder Level values in Inventory_Data (columns F, G) - all formulas recalculate.
A34: 2. Adjust Low Stock Buffer % or Order-Up-To Multiple on the Settings sheet to tune alert sensitivity.
A35: 3. Edit supplier lead times on the Suppliers sheet; Avg Daily Sales (blue, column L) can be replaced with real sales data.
A36: 4. Open Dashboard for the summary, Alert_Report for the action list, Stock_Lookup to check a single item.
